Workbook
Name consulta: MOVIMENTACOES!$J$294:$K$302
Name produto: PRODUTOS!$A$1:$H$239

Sheet PRODUTOS
A1: Código do Produto | B1: Nome do Item | C1: Fornecedor | D1: Unidade de Medida | E1: Categoria | F1: Marca | G1: Localizção | H1: Descrição do Produto | I1: Column 9
A2: 200000018 | B2: Algodão Hidrófilo Bola 100gr | C2: SIGBP | D2: UN | E2: CONSUMO | F2: Nathy | G2: ARMARIO (A) | H2: Algodão Hidrófilo Bola 100g Farol é ideal para a higienização e assepsia da pele, remoção de maquiagem, esmalte e higiene do bebê. Composto por fibras 100% algodão purificadas e alvejadas, seu formato em bolas facilita a utilização, tornando-o prático para diversos procedimentos de cuidados pessoais e médicos. Adequado para ambientes hospitalares e uso doméstico, garante alta absorção e suavidade. Características: Fibras 100% algodão purificadas e alvejadas; Formato em bolas que facilita a utilização; Ideal para higienização e assepsia da pele, remoção de maquiagem e esmaltes; Adequado para uso médico-hospitalar. Especificações Técnicas: Material: 100% algodão; Peso: 100g; Registro ANVISA: 10341660006.
A3: 200000001 | B3: LIXA D'AGUA 150 | C3: CORDEIRO MAQUINAS E FERRAMENTAS | D3: UN | E3: CONSUMO | F3: BOSCH | G3: A(6-3) | H3: C423 Contém 25 folhas um pct, do tamanho 225 mm x 275 mm Composição: Costado de papel látex á prova d'água, óxido de alumínio e adesivos. Garantia, grão e validade: vide costado de luxa. Amazenar em lugar seco e ventilado.
A4: 200007285 | B4: LIXA D'MADEIRA 120 | C4: CORDEIRO MAQUINAS E FERRAMENTAS | D4: UN | E4: CONSUMO | F4: BOSCH | G4: A(6-4) | H4: D411 Contém 25 folhas um pct, do tamanho 225 mm x 275 mm Composição: Costado de papel látex á prova d'água, óxido de alumínio e adesivos. Garantia, grão e validade: vide costado de luxa. Amazenar em lugar seco e ventilado.
A5: 200000006 | B5: OLEO MINERAL 70PS | C5: CASASLEO | D5: UN | E5: CONSUMO | F5: NÃO INFORMADO | G5: Faltando
A6: 200002700 | B6: THINNER / LIMPEZA E ACABAMENTO 900ML | C6: CORDEIRO MAQUINAS E FERRAMENTAS | D6: UN | E6: CONSUMO | F6: ITAQUA | G6: A(10-1) | H6: FAB: 11/2024 VAL: 3 ANOS IT 16 (thinner-multiuso) IT 800 (thinner - diluição) IT 37 (thinner acabamento automotivo)
A7: 200026827 | B7: TRINCHA 3 | C7: CORDEIRO MAQUINAS E FERRAMENTAS | D7: UN | E7: CONSUMO | F7: ATLAS | G7: A(6-4) | H7: PCT COM 12 UNIDADE Aspectos: Suas cerdas mistas são suaves, macias, proporcionam boa absorção e retenção de tinta, evitam desperdício de tempo e dinheiro. Coberturas e acabamentos uniformes, deslizamento suave e material resistente são algumas das principais características deste pincel.
A8: 200024290 | B8: TRINCHA 3/4 | C8: CORDEIRO MAQUINAS E FERRAMENTAS | D8: UN | E8: CONSUMO | F8: ATLAS | G8: A(6-3) | H8: PCT COM 12 UNIDADE Trincha para Pintura Média 3/4" Atlas possui cerdas brancas selecionadas que oferecem uma melhor performance no momento da pintura. O produto é ideal no uso de verniz e stain para você deixar a reforma ou o acabamento da sua decoração do jeito que você gosta.
A9: 200065892 | B9: FITA ISOLANTE 18MMX20M COR PRETA | C9: SIGBP | D9: UN | E9: CONSUMO | G9: ARMARIO (B) | H9: FITA ISOLANTE 18MMX20M COR PRETA
A10: 200076172 | B10: LUVA DE VINIL G(9) COM 100 UND | C10: SIGBP | D10: UN | E10: EPI | F10: NOBRE | G10: ARMARIO (B) | H10: LUVA DE VINIL G(9) COM 100 UND
A11: 200052414 | B11: LUVA LATEX M(8) COM 100 UND | C11: SIGBP | D11: UN | E11: EPI | F11: NOBRE | G11: ARMARIO (B) | H11: LUVA DE VINIL M(8) COM 100 UND
A12: 200052413 | B12: LUVA LATEX P COM 100 UND | C12: SIGBP | D12: UN | E12: EPI | F12: HEALTHCARE | G12: ARMARIO (B) | H12: LUVA PARA PROCEDIMENTO NÃO CURÚRGICO EM LATEX COM PO TAMANHO P COM 100 UNIDADES
A13: 200037491 | B13: MASCARA CIRURGICA TRIPLA | C13: SIGBP | D13: UN | E13: EPI | F13: NOBRE | G13: ARMARIO (B) | H13: MASCARA CIRURGICA DESCARTAVEL COM 3 CAMADAS RETANGULAR COM ELASTICO EMBALAGEM COM 50UN
A14: 200075793 | B14: MASCARA DE PROTEÇÃO PFF2 FILTRO N95 COM VALVULA SUPER SAFETY (azul) | C14: SIGBP | D14: PCT | E14: EPI | F14: AIRPROT | G14: ARMARIO (B) | H14: MASCARA DE PROTEÇÃO PFF2 FILTRO N95 COM VALVULA SUPER SAFETY CA
A15: 200061889 | B15: MASCARA DE PROTEÇÃO PFF2 FILTRO N95( BRANCA) | C15: SIGBP | D15: UN | E15: EPI | F15: 2 - NUTRIEX 5 - CHIKOOL | G15: ARMARIO (B) | H15: MASCARA DE PROTEÇÃO PFF2 FILTRO N95
A16: 200070939 | B16: MASCARA DE PROTEÇÃO PFR95 FILTRO N95 (PRETA) | C16: SIGBP | D16: UN | E16: EPI
A17: 200065969 | B17: OCULOS DE PROTEÇÃO JAGUAR | C17: SIGBP | D17: UN | E17: EPI | F17: KAPIPSO epi | G17: ARMARIO (B) | H17: OCULOS DE PROTEÇÃO POLICARBONATO INCOLOR TIPO CARBOGRAFITE
A18: 200052480 | B18: PROTETOR AURICULAR DE SILICONE TIPO PLUG | C18: SIGBP | D18: UN | E18: EPI | F18: SUPERMEDY | G18: ARMARIO (B) | H18: PROTETOR AURICULAR DE SILICONE TIPO PLUG
A19: 200052481 | B19: PROTETOR AURICULAR TIPO CONCHA | C19: SIGBP | D19: CX | E19: EPI | F19: CONFORTPLUS | G19: ARMARIO (B) | H19: ABAFADOR DE RUIDO TIPO CONCHA
A20: 200000700 | B20: TOUCA DESCARTAVEL PACOTE COM 100 UN | C20: SIGBP | D20: UN | E20: EPI | G20: ARMARIO (A) | H20: A Touca Descartável da Descarpack é um artigo médico utilizado para impedir a queda de cabelos em locais que precisam de alta limpeza e, assim, evitar possíveis contaminações ou acidentes. A touca é voltada para uso por profissionais de áreas diversas. Características e detalhes: * Fabricada em Tecido Não Tecido (TNT) 100% polipropileno; * Possui elástico revestido que garante maior vedação e conforto; * Confeccionada em material que permite a respiração do couro cabeludo; * Tamanho único; * Não estéril, descartável e de uso único. Indicações de uso: A Touca Descartável da Descarpack é indicada para uso em ambientes médicos e hospitalares – hospitais, clínicas, laboratórios, farmácias ou clínicas odontológicas. Pode ser usada também por profissionais das áreas de alimentação e nutrição. Especificações do produto: Pacote com 100 unidades. Cor: branca. Ref.: 0093201.
A21: 207218574 | B21: LUVA EPI ALGODÃO MALHA PIGMENTADA PRETA | C21: SIGBP | D21: UN | E21: EPI | G21: ARMARIO (B)
A22: 200043606 | B22: PASTA OFICIO EM PAPELAO COM TRILHO 250X340MM | C22: SIGBP | D22: UN | E22: EXPEDIENTE
A23: 200038284 | B23: ABRAÇADEIRA DE NYLON 100X2,5MM | C23: SIGBP | D23: UN | E23: EXPEDIENTE | G23: ARMARIO (B) | H23: ABRAÇADEIRA DE NYLON 100X2,5MM Pacote com 100unidade
A24: 200036752 | B24: ALCOOL 1LT | C24: SIGBP | D24: UN | E24: EXPEDIENTE | F24: BELLOBELLA INDUSTRIA DE COSMETICOS - 7 OUTRO - 1 OUTRO - 1 | G24: Faltando | H24: ALCOOL ETILICO A 70% DE 1LT
A25: 200069551 | B25: ALFINETE MARCADOR DE MAPA 8MM TIPO BOLA EM PLASTICO 50UN | C25: SIGBP | D25: CX | E25: EXPEDIENTE | F25: BACCHI | G25: ARMARIO (A) | H25: ALFINETE MARCADOR DE MAPA 8MM TIPO BOLA EM PLASTICO 50UN
A26: 200043234 | B26: ALFINETE PARA COSTURA CABO FINO Nº29 | C26: SIGBP | D26: CX | E26: EXPEDIENTE | F26: BACCHI | G26: ARMARIO (A) | H26: ALFINETE NIQUELADO, NÚMERO 29, 50 GRAMAS, MARCA BACCHI. PARA COSTURA
A27: 200056827 | B27: BORRACHA ESCOLAR BRANCA 34X23X8 | C27: SIGBP | D27: UN | E27: EXPEDIENTE | F27: PREMIER | G27: Faltando | H27: BORRACHA ESCOLAR BRANCA 34X23X8
A28: 200040799 | B28: CAIXA ARQUIVO MORTO EM POLIONDA MED (380X175X290) MM NA COR AMARELA | C28: SIGBP | D28: UN | E28: EXPEDIENTE | G28: B(2-3) | H28: CAIXA ARQUIVO MORTO EM POLIONDA MED (380X175X290) MM NA COR AMARELA
A29: 200036202 | B29: CANETA ESFEROGRAFICA PONTA MEDIA COR AZUL | C29: SIGBP | D29: CX | E29: EXPEDIENTE | F29: COMPACTOR ECONOMIC | G29: ARMARIO (A) | H29: CANETA ESFEROGRAFICA PONTA MEDIA COR AZUL
A30: 200036488 | B30: CANETA MARCADOR PERMANENTE PONTA 2.0mm | C30: SIGBP | D30: UN | E30: EXPEDIENTE | H30: marcador para retro projetor permanete ponta media 2.0mm
A31: 200038199 | B31: CANETA MARCADOR PERMANENTE PONTA GROSSA PRETO | C31: SIGBP | D31: UN | E31: EXPEDIENTE | F31: MASTERPRINT
A32: 200031692 | B32: CANETA PARA RETROPROJETOR FINA | C32: SIGBP | D32: UN | E32: EXPEDIENTE | H32: CANETA MARCADOR PERMANENTE PONTA GROSSA PRETO e AZUL(200031692)
A33: 200036201 | B33: CANETA ESFEROGRAFICA PONTA MEDIA COR PRETA | C33: SIGBP | D33: UN | E33: EXPEDIENTE | F33: COMPACTOR ECONOMIC | G33: ARMARIO (A-1) | H33: CANETA ESFEROGRAFICA PONTA MEDIA COR PRETA
A34: 200038178 | B34: CARTOLINA GRAMATURA 50X66CM DE 150G | C34: SIGBP | D34: UN | E34: EXPEDIENTE | G34: ARMARIO (A) | H34: CARTOLINA GRAMATURA 50X66CM DE 150G
A35: 200036489 | B35: CLIPS NIQUELADO Nº 1 COM 100 UN | C35: SIGBP | D35: CX | E35: EXPEDIENTE | F35: BACCHI | G35: ARMARIO (A) | H35: CLIPS NIQUELADO N°1 COM 100UND
A36: 200036490 | B36: CLIPS NIQUELADO Nº 2 COM 100 UN | C36: SIGBP | D36: CX | E36: EXPEDIENTE | F36: ECCOCLIPS | G36: ARMARIO (A) | H36: CLIPS NIQUELADO Nº 2 COM 100 UN
A37: 200037413 | B37: CLIPS NIQUELADO Nº 3 COM 50 UN | C37: SIGBP | D37: CX | E37: EXPEDIENTE | F37: ECCOCLIPS | G37: ARMARIO (A) | H37: CLIPS NIQUELADO Nº 3 COM 50 UN
A38: 200039379 | B38: CLIPS NIQUELADO Nº 8 COM 25 UN | C38: SIGBP | D38: CX | E38: EXPEDIENTE | G38: ARMARIO (A) | H38: CLIPS NIQUELADO Nº 8 COM 25 UN
A39: 200036793 | B39: COLHER DESCARTAVEL 12CM COM 50 UNIDADES | C39: SIGBP | D39: PCT | E39: EXPEDIENTE | G39: ARMARIO (B)
A40: 200036792 | B40: GARFO DESCARTAVEL 15CM COM 50 UNIDADES | C40: SIGBP | D40: PCT | E40: EXPEDIENTE | G40: ARMARIO (B)
A41: 200036791 | B41: PAPEL GUARDANAPO DE 20X22CM COM 50 FOLHAS | C41: SIGBP | D41: PCT | E41: EXPEDIENTE | G41: ARMARIO (B)
A42: 200009230 | B42: PRATO DESCARTAVEL 12CM FUNDO | C42: SIGBP | D42: PCT | E42: EXPEDIENTE | G42: ARMARIO (B)
A43: 200036941 | B43: COLA BRANCA BASTAO 10G | C43: SIGBP | D43: UN | E43: EXPEDIENTE | F43: LEONORA | G43: ARMARIO (A-1) | H43: COLA BRANCA BASTAO 10G
A44: 200036416 | B44: COLA BRANCA PVA EMBALAGEM DE 1KG | C44: SIGBP | D44: UN | E44: EXPEDIENTE | F44: PIRA | G44: Faltando | H44: COLA BRANCA PVA EMBALAGEM DE 1KG
A45: 200036189 | B45: COPO DESCARTAVEL 180ML | C45: SIGBP | D45: UN | E45: EXPEDIENTE | F45: DESC | G45: ARMARIO (A) | H45: COPO DESCARTAVEL DE 180ML (100 UNIDADES)
A46: 200052793 | B46: CORRETIVO EM FITA 5MMX12M | C46: SIGBP | D46: UN | E46: EXPEDIENTE | F46: DESC | G46: Faltando | H46: CORRETIVO EM FITA 5MMX12M
A47: 200060665 | B47: CORRETIVO LIQUIDO DE 18ML | C47: SIGBP | D47: UN | E47: EXPEDIENTE | G47: ARMARIO (A) | H47: CORRETIVO LIQUIDO DE 18ML
A48: 200041824 | B48: ELASTICOS AMARELO | C48: SIGBP | D48: PCT | E48: EXPEDIENTE | F48: PREMIER | G48: Faltando | H48: ELASTICOS N°18 COM 30 UNIDADES LIGA ELASTICA DE BORRACHA ANAREÇA N18 DE 25G
A49: 200066236 | B49: ENVELOPE MADEIRA A4 240 X 340MM 80G | C49: SIGBP | D49: UN | E49: EXPEDIENTE | G49: Faltando | H49: ENVELOPE MADEIRA A4 240 X 340MM 80G
A50: 200085185 | B50: ESPARADRAPO IMPERMEAVEL 5CM X 4,5M | C50: SIGBP | D50: UN | E50: EXPEDIENTE | F50: 2 - MAXICOR 3-MISSNER | G50: ARMARIO (A) | H50: ESPARADRAPO IMPERMEAVEL 5CM X 4,5M
A51: 200036618 | B51: ESPONJA SINTETICA DUPLA FACE 10X7X2 | C51: SIGBP | D51: UN | E51: EXPEDIENTE | G51: ARMARIO (A) | H51: ESPONJA SINTETICA DUPLA FACE 10X7X2
A52: 200054364 | B52: ESTILETE PLASTICO DE 13CM LAMINA LARGA | C52: SIGBP | D52: UN | E52: EXPEDIENTE | F52: DESCONHECIDO | G52: Faltando | H52: ESTILETE PLASTICO ESTREITO
A53: 200048673 | B53: ESTILETE PLASTICO ESTREITO DE 9MM | C53: SIGBP | D53: PCT | E53: EXPEDIENTE | F53: DESCONHECIDO | G53: ARMARIO (A-1) | H53: ESTILETE PLASTICO ESTREITO DE 9MM
A54: 200038156 | B54: EXTRATOR DE GRAMPO ESPATULA EM AÇO DE 15cm | C54: SIGBP | D54: UN | E54: EXPEDIENTE | G54: ARMARIO (A) | H54: EXTRATOR DE GRAMPO ESPATULA EM AÇO DE 15cm
A55: 200037892 | B55: FITA ADESIVA CREPE 19MM X 50M | C55: SIGBP | D55: UN | E55: EXPEDIENTE | G55: ARMARIO (A) | H55: FITA ADESIVA CREPE 19MM X 50M
A56: 200036656 | B56: FITA ADESIVA TRANSPARENTE 45MM X 50M | C56: SIGBP | D56: UN | E56: EXPEDIENTE | G56: ARMARIO (A) | H56: FITA ADESIVA TRANSPARENTE 45MM X 50M
A57: 200056391 | B57: FITA CREPE DE 48X50MM | C57: SIGBP | D57: UN | E57: EXPEDIENTE | G57: ARMARIO (A) | H57: FITA CREPE DE 48X50MM
A58: 200033068 | B58: PAPEL SULFITE A4 210 X 297MM 75G BRANCO MULTIUSO PACOTE COM 500 FLS | C58: SIGBP | D58: UN | E58: EXPEDIENTE | F58: REPORT | G58: ARMARIO (A-1) | H58: PAPEL SULFITE A4 210 X 297MM 75G BRANCO MULTIUSO PACOTE COM 500 FLS
A59: 200036577 | B59: GRAMPEADOR | C59: SIGBP | D59: UN | E59: EXPEDIENTE | G59: Faltando | H59: GRAMPEADOR DE MESA MEDIO 26/6
A60: 200036780 | B60: GRAMPO PARA GRAMPEADOR NIQUELADO 26/6 CAIXA COM 5000 PEÇAS | C60: SIGBP | D60: UN | E60: EXPEDIENTE | F60: 1 - BRW 1-MATERPRINT | G60: ARMARIO (A) | H60: GRAMPO PARA GRAMPEADOR NIQUELADO 26/6 CAIXA COM 5000 PEÇAS
A61: 200058015 | B61: KNESIO - FITA DE CINESIOLOGIA ROLO COM 5CM X 5M | C61: SIGBP | D61: UN | E61: EXPEDIENTE | F61: DERMATAPE | G61: ARMARIO (A) | H61: FITA DE CINESIOLOGIA ROLO COM 5CM X 5M
A62: 200043598 | B62: LAMINA PARA ESTILETE ESTREITO DE 13CM | C62: SIGBP | D62: CX | E62: EXPEDIENTE | G62: ARMARIO (A) | H62: LAMINA PARA ESTILETE ESTREITO DE 13CM Cx com 10 und
A63: 200061185 | B63: LAMINA PARA ESTILETE ESTREITO DE 18CM | C63: SIGBP | D63: UN | E63: EXPEDIENTE | F63: DESCONHECIDO | G63: ARMARIO (A) | H63: LAMINA PARA ESTILETE ESTREITO DE 18CM
A64: 200001528 | B64: LAPIS GRAFITE Nº 02 | C64: SIGBP | D64: UN | E64: EXPEDIENTE | F64: BIC | G64: ARMARIO (A) | H64: LAPIS GRAFITE EM MADEIRA Nº 2
A65: 200036673 | B65: LIVRO ATA COM 200 FOLHAS NUMERADAS | C65: SIGBP | D65: UN | E65: EXPEDIENTE | G65: Faltando | H65: LIVRO ATA COM 200 FOLHAS NUMERADAS
A66: 200031707 | B66: MARCA TEXTO AZUL | C66: SIGBP | D66: UN | E66: EXPEDIENTE | H66: CANETA MARCA TEXTO MARCA TEXTO AZUL
A67: 200000009 | B67: MARCADOR PARA QUADRO BRANCO | C67: SIGBP | D67: UN | E67: EXPEDIENTE | F67: MASTERPRINT - COR - GREEN - 3 BLUE - 2 RED - 1 | H67: MARCADOR PARA QUADRO BRANCO
A68: 200064766 | B68: PASTA COM ELASTICO LONGA 335 X 245 X 55MM | C68: SIGBP | D68: UN | E68: EXPEDIENTE | G68: B(2-3) | H68: PASTA COM ELASTICO LONGA 335 X 245 X 55MM (vermelho)
A69: 200043839 | B69: PASTA POLIONDA COM ABA E ELASTICO 34X25X55MM | C69: SIGBP | D69: UN | E69: EXPEDIENTE | G69: Faltando | H69: Pasta azul
A70: 200066972 | B70: PASTA SANFONADA | C70: SIGBP | D70: UN | E70: EXPEDIENTE | H70: PASTA SANFONADA A4 COM 31 DIVISORIAS TRANSPARENTE 330x60x240mm
A71: 200074950 | B71: PILHA ALCALINA AA 1,5V COM 4 UNIDADES | C71: SIGBP | D71: PCT | E71: EXPEDIENTE | F71: OUROLUX | H71: PILHA ALCALINA AA 1,5V COM 4 UNIDADES
A72: 200062843 | B72: PILHA ALCALINA PALITO - AAA - LR03 04UN | C72: SIGBP | D72: PCT | E72: EXPEDIENTE | F72: PANASONIC | H72: Pilha Alcalina Panasonic Linha Power Alkaline Palito AAA - 1.5 Volts Cartela com 04 unidades LR03XAB/4B192. Panasonic é uma loja aceita globalmente que fornece produtos aprovados por um administrador de medicamentos reconhecido. Por favor, consulte o aviso de segurança. Pedimos que você leia as instruções cuidadosamente antes de usar.
A73: 200082939 | B73: BLOCO DE PAPEL AUTO ADESIVO POST IT 38X50MM 100 FOLHAS | C73: SIGBP | D73: PCT | E73: EXPEDIENTE | F73: JOGAROFICCE - 1 MASTERPRINT - 1 | G73: ARMARIO (A) | H73: BLOCO DE ANOTAÇÃO AUTOADESIVO 5CM X 50MM 4 BLOCOS COM 100UN
A74: 200081830 | B74: BLOCO DE ANOTAÇÃO AUTOADESIVO 76 X 102 MM COM 100 FOLHAS | C74: SIGBP | D74: PCT | E74: EXPEDIENTE | F74: MASTERPRINT - 1 | G74: ARMARIO (A) | H74: BLOCO DE ANOTAÇÃO AUTOADESIVO 76 X 102 MM COM 100 FOLHAS
A75: 200000047 | B75: POTES DE VIDRO 210ml | C75: DOAÇÃO | D75: UN | E75: EXPEDIENTE | H75: 12 potes de vidro planezza 210 ml + Tampas Metálicas e lacres Preto
A76: 200052513 | B76: PRANCHETA EM MADEIRA 33X23CM | C76: SIGBP | D76: UN | E76: EXPEDIENTE | H76: PRANCHETA EM MADEIRA 33X23CM
A77: 200001052 | B77: REGUA CRISTAL 50 CM | C77: SIGBP | D77: PCT | E77: EXPEDIENTE | F77: waleu ubd. brasileira | H77: REGUA CRISTAL 50 CM
A78: 200036733 | B78: CANETA MARCA TEXTO PLASTICA COR AMARELO | C78: SIGBP | D78: UN | E78: EXPEDIENTE | G78: ARMARIO (A) | H78: CANETA MARCA TEXTO PLASTICA COR AMARELO
A79: 200066176 | B79: TESOURA MULTIUSO SEM PONTA | C79: SIGBP | D79: UN | E79: EXPEDIENTE | G79: A(7-3)
A80: 200062977 | B80: TINTA PARA CARIMBO COR AZUL DE 40ML | C80: SIGBP | D80: UN | E80: EXPEDIENTE | G80: ARMARIO (A) | H80: TINTA PARA CARIMBO COR AZUL DE 40ML
A81: 200000408 | B81: LENÇOL DESCARTAVEL 50 x 70 mm | C81: SIGBP | D81: UN | E81: LIMPEZA
A82: 200036530 | B82: ODORIZADOR DE AMBIENTE AEROSOL DE 400ML | C82: SIGBP | D82: UN | E82: LIMPEZA | H82: ODORIZADOR DE AMBIENTE AEROSOL DE 400ML
A83: 200000019 | B83: Papel Toalha Interfolhado | C83: SIGBP | D83: RL | E83: LIMPEZA | H83: Papel Toalha Interfolhado
A84: 200070056 | B84: PAPEL TOALHADE ROLHO | C84: SIGBP | D84: UN | E84: LIMPEZA | H84: PAPEL TOALHA FOLHA DUPLA 21CM X 20CM COR BRANCA 50 FOLHAS DE ROLOS
A85: 200061213 | B85: SABONETE LIQUIDO CONCENTRADO 1L | C85: SIGBP | D85: UN | E85: LIMPEZA | H85: SABONETE LIQUIDO CONCENTRADO 1L
A86: 200001302 | B86: FORRAÇÃO ADESIVO 3M | C86: SIGBP | D86: UN | E86: MATERIAL T.O
A87: 200000054 | B87: FITA DE BORDA 1,5 x 2,5 x 1mm | C87: ARTICULATO | D87: UN | E87: MATERIAL T.O | H87: FITA DE BORDA 1,5 x 2,5 x 1mm
A88: 200000048 | B88: ORFICAST BLACK 300cm x 3cm FITA TERMOPLASTICA | C88: EFECTIV | D88: UN | E88: MATERIAL T.O | F88: ORFIT | H88: ORFICAST BLACK 300cm x 3cm FITA TERMOPLASTICA
A89: 200000050 | B89: ORFICAST BLUE 300cm x 3cm FITA TERMOPLASTICA | C89: EFECTIV | D89: UN | E89: MATERIAL T.O | F89: ORFIT | H89: ORFICAST BLUE 300cm x 3cm FITA TERMOPLASTICA
A90: 200000049 | B90: ORFICAST MORE (DUPLA CAMADA) BLACK 300cm x 15cm FITA TERMOPLASTICA | C90: EFECTIV | D90: UN | E90: MATERIAL T.O | F90: ORFIT | H90: ORFICAST MORE (DUPLA CAMADA) BLACK 300cm x 15cm FITA TERMOPLASTICA
A91: 200000051 | B91: ORFICAST ORANGE 300cm x 6cm FITA TERMOPLASTICA | C91: EFECTIV | D91: UN | E91: MATERIAL T.O | F91: ORFIT | H91: ORFICAST ORANGE 300cm x 6cm FITA TERMOPLASTICA
A92: 200000055 | B92: PEÇA / MATERIAL PARA ORTESES tipo FORRAÇÃO AUTO-ADESIVA ESP | C92: ARTICULATO | D92: UN | E92: MATERIAL T.O | H92: PEÇA/MATERIAL PARA ORTESES, TIPO FORRAÇÃO MATERIAL ALGODÃO E ESPUMA, CARACTERSITICA ADCIONAL AUTO-ADESIVA, ESP
A93: 200000024 | B93: PLACA TERMOPLASTICA - ORFIT ECO BLACK NS 45 x 60cm x 2.4 mm | C93: EFECTIV | D93: UN | E93: MATERIAL T.O | F93: ORFIT | H93: PLACA TERMOPLASTICA - ORFIT ECO BLACK NS 45 x 60cm x 3.2mm (SEM FURO)
A94: 200000025 | B94: PLACA TERMOPLASTICA - ORFIT ECO BLACK NS 45 x 60cm x 3.2mm MINI Perforated | C94: EFECTIV | D94: UN | E94: MATERIAL T.O | F94: ORFIT | H94: PLACA TERMOPLASTICA - ORFIT ECO BLACK NS 45 x 60cm x 3.2mm MINI Perforated / Cor - Black
A95: 200000026 | B95: PLACA TERMOPLASTICA - ORFIT ECO NATUREL 45 x 60 cm 2.4 mm | C95: EFECTIV | D95: UN | E95: MATERIAL T.O | F95: ORFIT | H95: PLACA TERMOPLASTICA - ORFIT ECO NATUREL 45 x 60cm x 2,4mm / COR - BEGE
A96: 200000027 | B96: PLACA TERMOPLASTICA - ORFIT ECO NATUREL 45 x 60cm x 3.2mm MINI Perforated | C96: EFECTIV | D96: UN | E96: MATERIAL T.O | F96: ORFIT | H96: PLACA TERMOPLASTICA - ORFIT ECO NATUREL 45 x 60cm x 3,2mm MINI Perforated / COR - BEGE
A97: 200000056 | B97: TESOURA /P CORTE TERMOPLASTICO FRIO | C97: ARTICULATO | D97: UN | E97: MATERIAL T.O | H97: TESOURA, MATERIAL AÇO INOXIDAVEL, COMPRIMENTO 19, TIPO PONTA LAMINA 6,4cm, COM MOLA, APLICAÇÃO P/CORTE TERMOPLASTICO FRIO
A98: 200000058 | B98: VELCRO FEMEA 50mm Verde Escuro | C98: ARTICULATO | D98: UN | E98: MATERIAL T.O | H98: VELCRO FEMEA 50mm ROSA V708
A99: 200000060 | B99: VELCRO FEMEA 50mm VERMELHO | C99: ARTICULATO | D99: UN | E99: MATERIAL T.O | H99: VELCRO FEMEA 50mm VERMELHO V736
A100: 200000057 | B100: VELCRO FEMEA 50mm AZUL MARINHO V182 | C100: ARTICULATO | D100: UN | E100: MATERIAL T.O | H100: VELCRO FEMEA 50mm AZUL M. V182
...

Sheet MOVIMENTACOES
A1: Data | B1: ANO | C1: Código do Produto | D1: Nome do Produto | E1: Tipo | F1: Quantidade | G1: Local/Profissional | H1: OBS | I1: Coluna 1
B2: =TEXT(A2, "yyyy-mm") -> 1899-12 | D2: =IFERROR(VLOOKUP(C2,produto,2,FALSE), "Produto não encontrado") -> Produto não encontrado
A3: 46175 | B3: =TEXT(A3, "yyyy-mm") -> 2026-06 | C3: 200000088 | D3: =IFERROR(VLOOKUP(C3,produto,2,FALSE), "Produto não encontrado") -> (MTP-10)MALHA ORTOPEDICA TUBULAR 10CM | E3: Entrada | F3: 2 | G3: Devolveu Curso
A4: 46175 | B4: =TEXT(A4, "yyyy-mm") -> 2026-06 | C4: 200000066 | D4: =IFERROR(VLOOKUP(C4,produto,2,FALSE), "Produto não encontrado") -> ATADURA GESSADA 15cm x 3m, cx com 20 und | E4: Entrada | F4: 2 | G4: Devolveu Curso
A5: 46175 | B5: =TEXT(A5, "yyyy-mm") -> 2026-06 | C5: 200000081 | D5: =IFERROR(VLOOKUP(C5,produto,2,FALSE), "Produto não encontrado") -> ATADURA GESSADA 20cm x 2m, cx com 10 und | E5: Entrada | F5: 1 | G5: Devolveu Curso
A6: 46171 | B6: =TEXT(A6, "yyyy-mm") -> 2026-05 | C6: 200000088 | D6: =IFERROR(VLOOKUP(C6,produto,2,FALSE), "Produto não encontrado") -> (MTP-10)MALHA ORTOPEDICA TUBULAR 10CM | E6: Saída | F6: 1 | G6: Ribamar / Saida para o curso | H6: Curso TOP
A7: 46171 | B7: =TEXT(A7, "yyyy-mm") -> 2026-05 | C7: 200000096 | D7: =IFERROR(VLOOKUP(C7,produto,2,FALSE), "Produto não encontrado") -> RESINA RIGIDA PARA LAMINAÇÃO | E7: Saída | F7: 1 | G7: Ribamar / Saida para o curso | H7: Curso TOP
A8: 46170 | B8: =TEXT(A8, "yyyy-mm") -> 2026-05 | C8: 200000088 | D8: =IFERROR(VLOOKUP(C8,produto,2,FALSE), "Produto não encontrado") -> (MTP-10)MALHA ORTOPEDICA TUBULAR 10CM | E8: Saída | F8: 1 | G8: Ribamar / Saida para o curso | H8: Curso TOP
A9: 46168 | B9: =TEXT(A9, "yyyy-mm") -> 2026-05 | C9: 200000082 | D9: =IFERROR(VLOOKUP(C9,produto,2,FALSE), "Produto não encontrado") -> VALVULA DE SUCÇÃO EM BORRACHA | E9: Saída | F9: 1 | G9: Ribamar / Saida para o curso | H9: Curso TOP
A10: 46168 | B10: =TEXT(A10, "yyyy-mm") -> 2026-05 | C10: 200000081 | D10: =IFERROR(VLOOKUP(C10,produto,2,FALSE), "Produto não encontrado") -> ATADURA GESSADA 20cm x 2m, cx com 10 und | E10: Saída | F10: 1 | G10: Ribamar / Saida para o curso | H10: Curso TOP
A11: 46168 | B11: =TEXT(A11, "yyyy-mm") -> 2026-05 | C11: 200000066 | D11: =IFERROR(VLOOKUP(C11,produto,2,FALSE), "Produto não encontrado") -> ATADURA GESSADA 15cm x 3m, cx com 20 und | E11: Saída | F11: 1 | G11: Ribamar / Saida para o curso | H11: Curso TOP
A12: 46164 | B12: =TEXT(A12, "yyyy-mm") -> 2026-05 | C12: 200000097 | D12: =IFERROR(VLOOKUP(C12,produto,2,FALSE), "Produto não encontrado") -> SILICONE SPRAY 300ML | E12: Saída | F12: 1 | G12: Ribamar / Saida para o curso | H12: Curso TOP
A13: 46163 | B13: =TEXT(A13, "yyyy-mm") -> 2026-05 | C13: 200085859 | D13: =IFERROR(VLOOKUP(C13,produto,2,FALSE), "Produto não encontrado") -> PE SACH COM DEDOS DIREITO | E13: Saída | F13: 1 | G13: Ribamar / Saida para o curso | H13: Curso TOP
A14: 46163 | B14: =TEXT(A14, "yyyy-mm") -> 2026-05 | C14: 200085861 | D14: =IFERROR(VLOOKUP(C14,produto,2,FALSE), "Produto não encontrado") -> PE SACH COM DEDOS ESQUERDO | E14: Saída | F14: 1 | G14: Ribamar / Saida para o curso | H14: Curso TOP
A15: 46163 | B15: =TEXT(A15, "yyyy-mm") -> 2026-05 | C15: 200000083 | D15: =IFERROR(VLOOKUP(C15,produto,2,FALSE), "Produto não encontrado") -> MANTA FIBRA DE VIDRO | E15: Saída | F15: 1 | G15: Ribamar / Saida para o curso | H15: Curso TOP
A16: 46163 | B16: =TEXT(A16, "yyyy-mm") -> 2026-05 | C16: 200000095 | D16: =IFERROR(VLOOKUP(C16,produto,2,FALSE), "Produto não encontrado") -> ENDURECEDOR PARA RESINA | E16: Saída | F16: 1 | G16: Ribamar / Saida para o curso | H16: Curso TOP
A17: 46163 | B17: =TEXT(A17, "yyyy-mm") -> 2026-05 | C17: 200000096 | D17: =IFERROR(VLOOKUP(C17,produto,2,FALSE), "Produto não encontrado") -> RESINA RIGIDA PARA LAMINAÇÃO | E17: Saída | F17: 1 | G17: Ribamar / Saida para o curso | H17: Curso TOP
... A23: 46161 | B23: =TEXT(A23, "yyyy-mm") -> 2026-05 | C23: 200000066 | D23: =IFERROR(VLOOKUP(C23,produto,2,FALSE), "Produto não encontrado") -> ATADURA GESSADA 15cm x 3m, cx com 20 und | E23: Saída | F23: 1 | G23: Juliano / Saida para o curso | H23: Curso TOP
A24: 46156 | B24: =TEXT(A24, "yyyy-mm") -> 2026-05 | C24: 021000012 | D24: =IFERROR(VLOOKUP(C24,produto,2,FALSE), "Produto não encontrado") -> ESTOFAMENTO DE ASSENTO | E24: Saída | F24: 1
A25: 46156 | B25: =TEXT(A25, "yyyy-mm") -> 2026-05 | C25: 026000034 | D25: =IFERROR(VLOOKUP(C25,produto,2,FALSE), "Produto não encontrado") -> ESTOFAMENTO DE ENCOSTO | E25: Saída | F25: 1
A26: 46155 | B26: =TEXT(A26, "yyyy-mm") -> 2026-05 | C26: 200033068 | D26: =IFERROR(VLOOKUP(C26,produto,2,FALSE), "Produto não encontrado") -> PAPEL SULFITE A4 210 X 297MM 75G BRANCO MULTIUSO PACOTE COM 500 FLS | E26: Saída | F26: 1
A27: 46155 | B27: =TEXT(A27, "yyyy-mm") -> 2026-05 | C27: 200036189 | D27: =IFERROR(VLOOKUP(C27,produto,2,FALSE), "Produto não encontrado") -> COPO DESCARTAVEL 180ML | E27: Saída | F27: 1 | G27: Jucimeire Lins da Silva
A28: 46154 | B28: =TEXT(A28, "yyyy-mm") -> 2026-05 | C28: 200085970 | D28: =IFERROR(VLOOKUP(C28,produto,2,FALSE), "Produto não encontrado") -> COLA DE CONTATO MULTIUSO DE 2,8KG | E28: Saída | F28: 1
A29: 46150 | B29: =TEXT(A29, "yyyy-mm") -> 2026-05 | C29: 200036189 | D29: =IFERROR(VLOOKUP(C29,produto,2,FALSE), "Produto não encontrado") -> COPO DESCARTAVEL 180ML | E29: Saída | F29: 1 | G29: Expediente
A30: 46149 | B30: =TEXT(A30, "yyyy-mm") -> 2026-05 | C30: 200000065 | D30: =IFERROR(VLOOKUP(C30,produto,2,FALSE), "Produto não encontrado") -> ATADURA GESSADA 20cm x 4m, cx com 20 und | E30: Saída | F30: 1 | G30: RIBAMAR
A31: 46148 | B31: =TEXT(A31, "yyyy-mm") -> 2026-05 | C31: 200000054 | D31: =IFERROR(VLOOKUP(C31,produto,2,FALSE), "Produto não encontrado") -> FITA DE BORDA 1,5 x 2,5 x 1mm | E31: Saída | F31: 1 | G31: SARAH TO
A32: 46148 | B32: =TEXT(A32, "yyyy-mm") -> 2026-05 | C32: 200036577 | D32: =IFERROR(VLOOKUP(C32,produto,2,FALSE), "Produto não encontrado") -> GRAMPEADOR | E32: Entrada | F32: 2 | G32: Almox. OFORT
A33: 46148 | B33: =TEXT(A33, "yyyy-mm") -> 2026-05 | C33: 200043606 | D33: =IFERROR(VLOOKUP(C33,produto,2,FALSE), "Produto não encontrado") -> PASTA OFICIO EM PAPELAO COM TRILHO 250X340MM | E33: Entrada | F33: 10 | G33: Almox. OFORT
A34: 46148 | B34: =TEXT(A34, "yyyy-mm") -> 2026-05 | C34: 200070939 | D34: =IFERROR(VLOOKUP(C34,produto,2,FALSE), "Produto não encontrado") -> MASCARA DE PROTEÇÃO PFR95 FILTRO N95 (PRETA) | E34: Entrada | F34: 5 | G34: Almox. OFORT
A35: 46148 | B35: =TEXT(A35, "yyyy-mm") -> 2026-05 | C35: 200033068 | D35: =IFERROR(VLOOKUP(C35,produto,2,FALSE), "Produto não encontrado") -> PAPEL SULFITE A4 210 X 297MM 75G BRANCO MULTIUSO PACOTE COM 500 FLS | E35: Entrada | F35: 6 | G35: Almox. OFORT
A36: 46148 | B36: =TEXT(A36, "yyyy-mm") -> 2026-05 | C36: 200036793 | D36: =IFERROR(VLOOKUP(C36,produto,2,FALSE), "Produto não encontrado") -> COLHER DESCARTAVEL 12CM COM 50 UNIDADES | E36: Entrada | F36: 3 | G36: Almox. OFORT
A37: 46148 | B37: =TEXT(A37, "yyyy-mm") -> 2026-05 | C37: 200036792 | D37: =IFERROR(VLOOKUP(C37,produto,2,FALSE), "Produto não encontrado") -> GARFO DESCARTAVEL 15CM COM 50 UNIDADES | E37: Entrada | F37: 3 | G37: Almox. OFORT
A38: 46148 | B38: =TEXT(A38, "yyyy-mm") -> 2026-05 | C38: 200036791 | D38: =IFERROR(VLOOKUP(C38,produto,2,FALSE), "Produto não encontrado") -> PAPEL GUARDANAPO DE 20X22CM COM 50 FOLHAS | E38: Entrada | F38: 3 | G38: Almox. OFORT
A39: 46148 | B39: =TEXT(A39, "yyyy-mm") -> 2026-05 | C39: 200009230 | D39: =IFERROR(VLOOKUP(C39,produto,2,FALSE), "Produto não encontrado") -> PRATO DESCARTAVEL 12CM FUNDO | E39: Entrada | F39: 3 | G39: Almox. OFORT
A40: 46148 | B40: =TEXT(A40, "yyyy-mm") -> 2026-05 | C40: 200036793 | D40: =IFERROR(VLOOKUP(C40,produto,2,FALSE), "Produto não encontrado") -> COLHER DESCARTAVEL 12CM COM 50 UNIDADES | E40: Entrada | F40: 3 | G40: Almox. OFORT
... A46: 46169 | B46: =TEXT(A46, "yyyy-mm") -> 2026-05 | C46: 200001302 | D46: =IFERROR(VLOOKUP(C46,produto,2,FALSE), "Produto não encontrado") -> FORRAÇÃO ADESIVO 3M | E46: Entrada | F46: 5 | G46: compra da igreja
A47: 46169 | B47: =TEXT(A47, "yyyy-mm") -> 2026-05 | C47: 200000027 | D47: =IFERROR(VLOOKUP(C47,produto,2,FALSE), "Produto não encontrado") -> PLACA TERMOPLASTICA - ORFIT ECO NATUREL 45 x 60cm x 3.2mm MINI Perforated | E47: Entrada | F47: 15 | G47: compra da igreja
A48: 46169 | B48: =TEXT(A48, "yyyy-mm") -> 2026-05 | C48: 200000054 | D48: =IFERROR(VLOOKUP(C48,produto,2,FALSE), "Produto não encontrado") -> FITA DE BORDA 1,5 x 2,5 x 1mm | E48: Saída | F48: 1 | G48: SARAH TO
A49: 46139 | B49: =TEXT(A49, "yyyy-mm") -> 2026-04 | C49: 200000027 | D49: =IFERROR(VLOOKUP(C49,produto,2,FALSE), "Produto não encontrado") -> PLACA TERMOPLASTICA - ORFIT ECO NATUREL 45 x 60cm x 3.2mm MINI Perforated | E49: Saída | F49: 3 | G49: SARAH TO
A50: 46147 | B50: =TEXT(A50, "yyyy-mm") -> 2026-05 | C50: 200000080 | D50: =IFERROR(VLOOKUP(C50,produto,2,FALSE), "Produto não encontrado") -> ATADURA GESSADA 15cm x 2m, cx com 10 und | E50: Saída | F50: 1 | G50: VANDELEY
A51: 46148 | B51: =TEXT(A51, "yyyy-mm") -> 2026-05 | C51: 200000040 | D51: =IFERROR(VLOOKUP(C51,produto,2,FALSE), "Produto não encontrado") -> ATADURA GESSADA 10cm x 3m, cx com 20 und | E51: Saída | F51: 1 | G51: RIBAMAR
A52: 46169 | B52: =TEXT(A52, "yyyy-mm") -> 2026-05 | C52: 200000080 | D52: =IFERROR(VLOOKUP(C52,produto,2,FALSE), "Produto não encontrado") -> ATADURA GESSADA 15cm x 2m, cx com 10 und | E52: Entrada | F52: 3 | G52: compra da igreja
A53: 46169 | B53: =TEXT(A53, "yyyy-mm") -> 2026-05 | C53: 200000040 | D53: =IFERROR(VLOOKUP(C53,produto,2,FALSE), "Produto não encontrado") -> ATADURA GESSADA 10cm x 3m, cx com 20 und | E53: Entrada | F53: 5 | G53: compra da igreja
A54: 46146 | B54: =TEXT(A54, "yyyy-mm") -> 2026-05 | C54: 200060665 | D54: =IFERROR(VLOOKUP(C54,produto,2,FALSE), "Produto não encontrado") -> CORRETIVO LIQUIDO DE 18ML | E54: Saída | F54: 1
A55: 46142 | B55: =TEXT(A55, "yyyy-mm") -> 2026-04 | C55: 200046152 | D55: =IFERROR(VLOOKUP(C55,produto,2,FALSE), "Produto não encontrado") -> MESA DE ATIVIDADES PARA CADEIRA DE RODAS | E55: Saída | F55: 1 | G55: Fisio Iara | H55: Usuario Henrique
A56: 46142 | B56: =TEXT(A56, "yyyy-mm") -> 2026-04 | C56: 200078042 | D56: =IFERROR(VLOOKUP(C56,produto,2,FALSE), "Produto não encontrado") -> MULETA CANADENSE ARTICULADA ALUMINIO REF: AG 6017 | E56: Saída | F56: 1 | G56: Fisio Iara | H56: Usuario Claudia Maria
A57: 46142 | B57: =TEXT(A57, "yyyy-mm") -> 2026-04 | C57: 035106000 | D57: =IFERROR(VLOOKUP(C57,produto,2,FALSE), "Produto não encontrado") -> CJ PEDAL ADULTO DIR/ESQ K2/K3 (PAR) | E57: Saída | F57: 1 | G57: TEC. Juliano
A58: 46142 | B58: =TEXT(A58, "yyyy-mm") -> 2026-04 | C58: 200000045 | D58: =IFERROR(VLOOKUP(C58,produto,2,FALSE), "Produto não encontrado") -> Malha Tubular de Algodão 10cm x 15m | E58: Saída | F58: 4 | G58: Retirada Tec. Vnadeley | H58: PRODUÇÃO PARA OFICINA
A59: 46142 | B59: =TEXT(A59, "yyyy-mm") -> 2026-04 | C59: 207218574 | D59: =IFERROR(VLOOKUP(C59,produto,2,FALSE), "Produto não encontrado") -> LUVA EPI ALGODÃO MALHA PIGMENTADA PRETA | E59: Saída | F59: 1 | G59: Retirada Ribamar
A60: 46142 | B60: =TEXT(A60, "yyyy-mm") -> 2026-04 | C60: 200000097 | D60: =IFERROR(VLOOKUP(C60,produto,2,FALSE), "Produto não encontrado") -> SILICONE SPRAY 300ML | E60: Saída | F60: 1 | G60: Retirada Ribamar
A61: 46142 | B61: =TEXT(A61, "yyyy-mm") -> 2026-04 | C61: 200033068 | D61: =IFERROR(VLOOKUP(C61,produto,2,FALSE), "Produto não encontrado") -> PAPEL SULFITE A4 210 X 297MM 75G BRANCO MULTIUSO PACOTE COM 500 FLS | E61: Saída | F61: 1 | G61: Recepção
A62: 46141 | B62: =TEXT(A62, "yyyy-mm") -> 2026-04 | C62: 200000040 | D62: =IFERROR(VLOOKUP(C62,produto,2,FALSE), "Produto não encontrado") -> ATADURA GESSADA 10cm x 3m, cx com 20 und | E62: Saída | F62: 1
A63: 46139 | B63: =TEXT(A63, "yyyy-mm") -> 2026-04 | C63: 026000034 | D63: =IFERROR(VLOOKUP(C63,produto,2,FALSE), "Produto não encontrado") -> ESTOFAMENTO DE ENCOSTO | E63: Saída | F63: 1 | G63: Jefferson de Almeida | H63: LARG: 40 x ALT: 40 Encosto
A64: 46139 | B64: =TEXT(A64, "yyyy-mm") -> 2026-04 | C64: 021000012 | D64: =IFERROR(VLOOKUP(C64,produto,2,FALSE), "Produto não encontrado") -> ESTOFAMENTO DE ASSENTO | E64: Saída | F64: 1 | G64: Jefferson de Almeida | H64: LARG: 40 x PROF: 40 Assento
A65: 46139 | B65: =TEXT(A65, "yyyy-mm") -> 2026-04 | C65: 026000034 | D65: =IFERROR(VLOOKUP(C65,produto,2,FALSE), "Produto não encontrado") -> ESTOFAMENTO DE ENCOSTO | E65: Saída | F65: 1 | G65: Jefferson de Almeida | H65: LARG: 38 x ALT: 40 Encosto
A66: 46139 | B66: =TEXT(A66, "yyyy-mm") -> 2026-04 | C66: 021000012 | D66: =IFERROR(VLOOKUP(C66,produto,2,FALSE), "Produto não encontrado") -> ESTOFAMENTO DE ASSENTO | E66: Saída | F66: 1 | G66: Jefferson de Almeida | H66: LARG: 38 x PROF: 40 Assento
A67: 46139 | B67: =TEXT(A67, "yyyy-mm") -> 2026-04 | C67: 011109001 | D67: =IFERROR(VLOOKUP(C67,produto,2,FALSE), "Produto não encontrado") -> CJ APOIO CABECA L33 AI | E67: Saída | F67: 1 | G67: Jefferson de Almeida | H67: Sarah?/ paciente do trauma
A68: 46139 | B68: =TEXT(A68, "yyyy-mm") -> 2026-04 | C68: 200064766 | D68: =IFERROR(VLOOKUP(C68,produto,2,FALSE), "Produto não encontrado") -> PASTA COM ELASTICO LONGA 335 X 245 X 55MM | E68: Saída | F68: 2
A69: 46135 | B69: =TEXT(A69, "yyyy-mm") -> 2026-04 | C69: 200041824 | D69: =IFERROR(VLOOKUP(C69,produto,2,FALSE), "Produto não encontrado") -> ELASTICOS AMARELO | E69: Saída | F69: 2 | G69: INVENTARIO/Jefferson de Almeida
A70: 46129 | B70: =TEXT(A70, "yyyy-mm") -> 2026-04 | C70: 200036618 | D70: =IFERROR(VLOOKUP(C70,produto,2,FALSE), "Produto não encontrado") -> ESPONJA SINTETICA DUPLA FACE 10X7X2 | E70: Saída | F70: 1 | G70: Almox. OFORT
A71: 46113 | B71: =TEXT(A71, "yyyy-mm") -> 2026-04 | C71: 200000050 | D71: =IFERROR(VLOOKUP(C71,produto,2,FALSE), "Produto não encontrado") -> ORFICAST BLUE 300cm x 3cm FITA TERMOPLASTICA | E71: Saída | F71: 1 | G71: Sainda P/ Terapeuta Ocupacional
A72: 46113 | B72: =TEXT(A72, "yyyy-mm") -> 2026-04 | C72: 200000050 | D72: =IFERROR(VLOOKUP(C72,produto,2,FALSE), "Produto não encontrado") -> ORFICAST BLUE 300cm x 3cm FITA TERMOPLASTICA | E72: Entrada | F72: 3 | G72: Compra da Igreja
A73: 46113 | B73: =TEXT(A73, "yyyy-mm") -> 2026-04 | C73: 200000098 | D73: =IFERROR(VLOOKUP(C73,produto,2,FALSE), "Produto não encontrado") -> LAMINA SURFORM | E73: Entrada | F73: 3 | G73: Compra da Igreja
A74: 46127 | B74: =TEXT(A74, "yyyy-mm") -> 2026-04 | C74: 200036189 | D74: =IFERROR(VLOOKUP(C74,produto,2,FALSE), "Produto não encontrado") -> COPO DESCARTAVEL 180ML | E74: Saída | F74: 4 | G74: Sainda P/ Oficina
A75: 46113 | B75: =TEXT(A75, "yyyy-mm") -> 2026-04 | C75: 200000097 | D75: =IFERROR(VLOOKUP(C75,produto,2,FALSE), "Produto não encontrado") -> SILICONE SPRAY 300ML | E75: Saída | F75: 1 | G75: Sainda P/ Oficina
A76: 46113 | B76: =TEXT(A76, "yyyy-mm") -> 2026-04 | C76: 200000097 | D76: =IFERROR(VLOOKUP(C76,produto,2,FALSE), "Produto não encontrado") -> SILICONE SPRAY 300ML | E76: Entrada | F76: 6 | G76: Compra da Igreja
A77: 46127 | B77: =TEXT(A77, "yyyy-mm") -> 2026-04 | C77: 200078043 | D77: =IFERROR(VLOOKUP(C77,produto,2,FALSE), "Produto não encontrado") -> MULETA AXILAR EM ALUMINIO REF: AG 6008 | E77: Entrada | F77: 14 | G77: Almox. FUNAD
A78: 46127 | B78: =TEXT(A78, "yyyy-mm") -> 2026-04 | C78: 200078042 | D78: =IFERROR(VLOOKUP(C78,produto,2,FALSE), "Produto não encontrado") -> MULETA CANADENSE ARTICULADA ALUMINIO REF: AG 6017 | E78: Saída | F78: 1 | G78: Coord. Fabia
A79: 46127 | B79: =TEXT(A79, "yyyy-mm") -> 2026-04 | C79: 200078042 | D79: =IFERROR(VLOOKUP(C79,produto,2,FALSE), "Produto não encontrado") -> MULETA CANADENSE ARTICULADA ALUMINIO REF: AG 6017 | E79: Entrada | F79: 20 | G79: Almox. FUNAD
A80: 46126 | B80: =TEXT(A80, "yyyy-mm") -> 2026-04 | C80: 200062843 | D80: =IFERROR(VLOOKUP(C80,produto,2,FALSE), "Produto não encontrado") -> PILHA ALCALINA PALITO - AAA - LR03 04UN | E80: Entrada | F80: 3 | G80: Almox. FUNAD
... A97: 46125 | B97: =TEXT(A97, "yyyy-mm") -> 2026-04 | C97: 121218110 | D97: =IFERROR(VLOOKUP(C97,produto,2,FALSE), "Produto não encontrado") -> MOLDE DE ESPUMA UNICO/UNICO | E97: Entrada | F97: 100 | G97: DILEPÉ
A98: 46125 | B98: =TEXT(A98, "yyyy-mm") -> 2026-04 | C98: 021000012 | D98: =IFERROR(VLOOKUP(C98,produto,2,FALSE), "Produto não encontrado") -> ESTOFAMENTO DE ASSENTO | E98: Entrada | F98: 28 | G98: ORTOBRAS
A99: 46125 | B99: =TEXT(A99, "yyyy-mm") -> 2026-04 | C99: 026000034 | D99: =IFERROR(VLOOKUP(C99,produto,2,FALSE), "Produto não encontrado") -> ESTOFAMENTO DE ENCOSTO | E99: Entrada | F99: 32 | G99: ORTOBRAS
A100: 46122 | B100: =TEXT(A100, "yyyy-mm") -> 2026-04 | C100: 200000096 | D100: =IFERROR(VLOOKUP(C100,produto,2,FALSE), "Produto não encontrado") -> RESINA RIGIDA PARA LAMINAÇÃO | E100: Entrada | F100: 2 | G100: SES - Secretaria de Estado da Saude
A101: 46122 | B101: =TEXT(A101, "yyyy-mm") -> 2026-04 | C101: 200000095 | D101: =IFERROR(VLOOKUP(C101,produto,2,FALSE), "Produto não encontrado") -> ENDURECEDOR PARA RESINA | E101: Entrada | F101: 2 | G101: SES - Secretaria de Estado da Saude
A102: 46122 | B102: =TEXT(A102, "yyyy-mm") -> 2026-04 | C102: 200000094 | D102: =IFERROR(VLOOKUP(C102,produto,2,FALSE), "Produto não encontrado") -> CONE DE PVC PARA LAMINAÇÃO (P) | E102: Entrada | F102: 10 | G102: SES - Secretaria de Estado da Saude
A103: 46122 | B103: =TEXT(A103, "yyyy-mm") -> 2026-04 | C103: 200000093 | D103: =IFERROR(VLOOKUP(C103,produto,2,FALSE), "Produto não encontrado") -> CONE DE PVC PARA LAMINAÇÃO (M) | E103: Entrada | F103: 10 | G103: SES - Secretaria de Estado da Saude
A104: 46122 | B104: =TEXT(A104, "yyyy-mm") -> 2026-04 | C104: 200000092 | D104: =IFERROR(VLOOKUP(C104,produto,2,FALSE), "Produto não encontrado") -> CONE DE PVC PARA LAMINAÇÃO (G) | E104: Entrada | F104: 10 | G104: SES - Secretaria de Estado da Saude
A105: 46122 | B105: =TEXT(A105, "yyyy-mm") -> 2026-04 | C105: 200000091 | D105: =IFERROR(VLOOKUP(C105,produto,2,FALSE), "Produto não encontrado") -> (MTA-20)MALHA ORTOPEDICA TUBULAR EM FIO DE ALGODÃO 20cm | E105: Entrada | F105: 2 | G105: SES - Secretaria de Estado da Saude
A106: 46122 | B106: =TEXT(A106, "yyyy-mm") -> 2026-04 | C106: 200000090 | D106: =IFERROR(VLOOKUP(C106,produto,2,FALSE), "Produto não encontrado") -> (MTA-15)MALHA ORTOPEDICA TUBULAR EM FIO DE ALGODÃO 15cm | E106: Entrada | F106: 4 | G106: SES - Secretaria de Estado da Saude
A107: 46122 | B107: =TEXT(A107, "yyyy-mm") -> 2026-04 | C107: 200000089 | D107: =IFERROR(VLOOKUP(C107,produto,2,FALSE), "Produto não encontrado") -> (MTA-10)MALHA ORTOPEDICA TUBULAR EM FIO DE ALGODÃO 10cm | E107: Entrada | F107: 20 | G107: SES - Secretaria de Estado da Saude
A108: 46122 | B108: =TEXT(A108, "yyyy-mm") -> 2026-04 | C108: 200000086 | D108: =IFERROR(VLOOKUP(C108,produto,2,FALSE), "Produto não encontrado") -> (MTP-6)MALHA TUBULAR POLIESTER 6CM | E108: Entrada | F108: 5 | G108: SES - Secretaria de Estado da Saude
A109: 46122 | B109: =TEXT(A109, "yyyy-mm") -> 2026-04 | C109: 200000087 | D109: =IFERROR(VLOOKUP(C109,produto,2,FALSE), "Produto não encontrado") -> (MTP-8)MALHA TUBULAR POLIESTER 8CM | E109: Entrada | F109: 5 | G109: SES - Secretaria de Estado da Saude
A110: 46122 | B110: =TEXT(A110, "yyyy-mm") -> 2026-04 | C110: 200000088 | D110: =IFERROR(VLOOKUP(C110,produto,2,FALSE), "Produto não encontrado") -> (MTP-10)MALHA ORTOPEDICA TUBULAR 10CM | E110: Entrada | F110: 5 | G110: SES - Secretaria de Estado da Saude
A111: 46122 | B111: =TEXT(A111, "yyyy-mm") -> 2026-04 | C111: 200000085 | D111: =IFERROR(VLOOKUP(C111,produto,2,FALSE), "Produto não encontrado") -> (MTP-15)MALHA ORTOPEDICA TUBULAR 15CM | E111: Entrada | F111: 5 | G111: SES - Secretaria de Estado da Saude
... A117: 46121 | B117: =TEXT(A117, "yyyy-mm") -> 2026-04 | C117: 200000045 | D117: =IFERROR(VLOOKUP(C117,produto,2,FALSE), "Produto não encontrado") -> Malha Tubular de Algodão 10cm x 15m | E117: Saída | F117: 1 | G117: Salão Oficina/Sarah
A118: 46121 | B118: =TEXT(A118, "yyyy-mm") -> 2026-04 | C118: 000900008 | D118: =IFERROR(VLOOKUP(C118,produto,2,FALSE), "Produto não encontrado") -> CJ APOIO CABECA INJETADO P/ ESTICADOR | E118: Entrada | F118: 19 | G118: INVENTARIO/Jefferson de Almeida
A119: 46121 | B119: =TEXT(A119, "yyyy-mm") -> 2026-04 | C119: 011109001 | D119: =IFERROR(VLOOKUP(C119,produto,2,FALSE), "Produto não encontrado") -> CJ APOIO CABECA L33 AI | E119: Entrada | F119: 1 | G119: INVENTARIO/Jefferson de Almeida
A120: 46121 | B120: =TEXT(A120, "yyyy-mm") -> 2026-04 | C120: 035106000 | D120: =IFERROR(VLOOKUP(C120,produto,2,FALSE), "Produto não encontrado") -> CJ PEDAL ADULTO DIR/ESQ K2/K3 (PAR) | E120: Entrada | F120: 5 | G120: INVENTARIO/Jefferson de Almeida
A121: 46121 | B121: =TEXT(A121, "yyyy-mm") -> 2026-04 | C121: 035106006 | D121: =IFERROR(VLOOKUP(C121,produto,2,FALSE), "Produto não encontrado") -> CJ PEDAL DIR/ESQ INFANTIL K2/K3 (PAR) | E121: Entrada | F121: 3 | G121: INVENTARIO/Jefferson de Almeida
A122: 46121 | B122: =TEXT(A122, "yyyy-mm") -> 2026-04 | C122: 002000130 | D122: =IFERROR(VLOOKUP(C122,produto,2,FALSE), "Produto não encontrado") -> CJ ESTICADOR ENCOSTO APOIO CABECA L36/L40/L44 | E122: Entrada | F122: 19 | G122: INVENTARIO/Jefferson de Almeida
A123: 46121 | B123: =TEXT(A123, "yyyy-mm") -> 2026-04 | C123: 031106017 | D123: =IFERROR(VLOOKUP(C123,produto,2,FALSE), "Produto não encontrado") -> CJ PEDAL ELEVAVEL L30 MINIK V2 | E123: Entrada | F123: 2 | G123: INVENTARIO/Jefferson de Almeida
A124: 46121 | B124: =TEXT(A124, "yyyy-mm") -> 2026-04 | C124: 499009237 | D124: =IFERROR(VLOOKUP(C124,produto,2,FALSE), "Produto não encontrado") -> CAPA APOIO CABECA PRETO RT/FT | E124: Entrada | F124: 20 | G124: INVENTARIO/Jefferson de Almeida
A125: 46120 | B125: =TEXT(A125, "yyyy-mm") -> 2026-04 | C125: 499020130 | D125: =IFERROR(VLOOKUP(C125,produto,2,FALSE), "Produto não encontrado") -> CONJUNTO ADEQUAÇÃO POSTURAL | E125: Entrada | F125: 80 | G125: INVENTARIO/Jefferson de Almeida
A126: 46119 | B126: =TEXT(A126, "yyyy-mm") -> 2026-04 | C126: 499002089 | D126: =IFERROR(VLOOKUP(C126,produto,2,FALSE), "Produto não encontrado") -> CJ P/ FIXAR SEPARADOR PERNAS AR/VD | E126: Entrada | F126: 29 | G126: INVENTARIO/Jefferson de Almeida
A127: 46119 | B127: =TEXT(A127, "yyyy-mm") -> 2026-04 | C127: 499020130 | D127: =IFERROR(VLOOKUP(C127,produto,2,FALSE), "Produto não encontrado") -> CONJUNTO ADEQUAÇÃO POSTURAL | E127: Entrada | F127: 12 | G127: INVENTARIO/Jefferson de Almeida
A128: 46119 | B128: =TEXT(A128, "yyyy-mm") -> 2026-04 | C128: 200046152 | D128: =IFERROR(VLOOKUP(C128,produto,2,FALSE), "Produto não encontrado") -> MESA DE ATIVIDADES PARA CADEIRA DE RODAS | E128: Entrada | F128: 53 | G128: INVENTARIO/Jefferson de Almeida
A129: 46119 | B129: =TEXT(A129, "yyyy-mm") -> 2026-04 | C129: 200000025 | D129: =IFERROR(VLOOKUP(C129,produto,2,FALSE), "Produto não encontrado") -> PLACA TERMOPLASTICA - ORFIT ECO BLACK NS 45 x 60cm x 3.2mm MINI Perforated | E129: Saída | F129: 4
A130: 46119 | B130: =TEXT(A130, "yyyy-mm") -> 2026-04 | C130: 200056827 | D130: =IFERROR(VLOOKUP(C130,produto,2,FALSE), "Produto não encontrado") -> BORRACHA ESCOLAR BRANCA 34X23X8 | E130: Saída | F130: 3 | G130: INVENTARIO/Jefferson de Almeida
A131: 46119 | B131: =TEXT(A131, "yyyy-mm") -> 2026-04 | C131: 200066236 | D131: =IFERROR(VLOOKUP(C131,produto,2,FALSE), "Produto não encontrado") -> ENVELOPE MADEIRA A4 240 X 340MM 80G | E131: Saída | F131: 5 | G131: Daniel
...

Sheet ESTOQUE ATUAL
A1: Código do Produto | B1: Nome do Item | C1: Categoria | D1: Column 10 | E1: Entradas Totais | F1: Saídas Totais | G1: Saldo Atual | H1: Situação | I1: Fornecedor
A2: 200000018 | B2: =VLOOKUP(A2,produto,2,0) -> Algodão Hidrófilo Bola 100gr | C2: =IFERROR(VLOOKUP(A2,PRODUTOS!A:E,5,FALSE), "Categoria não encontrada") -> CONSUMO | D2: =IFERROR(VLOOKUP(A2,PRODUTOS!A:E,4,FALSE), "Categoria não encontrada") -> UN | E2: =SUMIFS(MOVIMENTACOES!F:F,MOVIMENTACOES!C:C,A2,MOVIMENTACOES!E:E,"Entrada") -> 2 | F2: =SUMIFS(MOVIMENTACOES!F:F,MOVIMENTACOES!C:C,A2,MOVIMENTACOES!E:E,"Saída") -> 0 | G2: =E2-F2 -> 2 | H2: =IF(G2=0, "Faltando", IF(G2<=3, "Atenção", "OK")) -> Atenção | I2: =VLOOKUP(A2, PRODUTOS!A:H, 3, FALSE) -> SIGBP
A3: 200065892 | B3: =VLOOKUP(A3,produto,2,0) -> FITA ISOLANTE 18MMX20M COR PRETA | C3: =IFERROR(VLOOKUP(A3,PRODUTOS!A:E,5,FALSE), "Categoria não encontrada") -> CONSUMO | D3: =IFERROR(VLOOKUP(A3,PRODUTOS!A:E,4,FALSE), "Categoria não encontrada") -> UN | E3: =SUMIFS(MOVIMENTACOES!F:F,MOVIMENTACOES!C:C,A3,MOVIMENTACOES!E:E,"Entrada") -> 3 | F3: =SUMIFS(MOVIMENTACOES!F:F,MOVIMENTACOES!C:C,A3,MOVIMENTACOES!E:E,"Saída") -> 2 | G3: =E3-F3 -> 1 | H3: =IF(G3=0, "Faltando", IF(G3<=3, "Atenção", "OK")) -> Atenção | I3: =VLOOKUP(A3, PRODUTOS!A:H, 3, FALSE) -> SIGBP
A4: 200037491 | B4: =VLOOKUP(A4,produto,2,0) -> MASCARA CIRURGICA TRIPLA | C4: =IFERROR(VLOOKUP(A4,PRODUTOS!A:E,5,FALSE), "Categoria não encontrada") -> EPI | D4: =IFERROR(VLOOKUP(A4,PRODUTOS!A:E,4,FALSE), "Categoria não encontrada") -> UN | E4: =SUMIFS(MOVIMENTACOES!F:F,MOVIMENTACOES!C:C,A4,MOVIMENTACOES!E:E,"Entrada") -> 10 | F4: =SUMIFS(MOVIMENTACOES!F:F,MOVIMENTACOES!C:C,A4,MOVIMENTACOES!E:E,"Saída") -> 8 | G4: =E4-F4 -> 2 | H4: =IF(G4=0, "Faltando", IF(G4<=3, "Atenção", "OK")) -> Atenção | I4: =VLOOKUP(A4, PRODUTOS!A:H, 3, FALSE) -> SIGBP
A5: 200065969 | B5: =VLOOKUP(A5,produto,2,0) -> OCULOS DE PROTEÇÃO JAGUAR | C5: =IFERROR(VLOOKUP(A5,PRODUTOS!A:E,5,FALSE), "Categoria não encontrada") -> EPI | D5: =IFERROR(VLOOKUP(A5,PRODUTOS!A:E,4,FALSE), "Categoria não encontrada") -> UN | E5: =SUMIFS(MOVIMENTACOES!F:F,MOVIMENTACOES!C:C,A5,MOVIMENTACOES!E:E,"Entrada") -> 4 | F5: =SUMIFS(MOVIMENTACOES!F:F,MOVIMENTACOES!C:C,A5,MOVIMENTACOES!E:E,"Saída") -> 2 | G5: =E5-F5 -> 2 | H5: =IF(G5=0, "Faltando", IF(G5<=3, "Atenção", "OK")) -> Atenção | I5: =VLOOKUP(A5, PRODUTOS!A:H, 3, FALSE) -> SIGBP
A6: 200052480 | B6: =VLOOKUP(A6,produto,2,0) -> PROTETOR AURICULAR DE SILICONE TIPO PLUG | C6: =IFERROR(VLOOKUP(A6,PRODUTOS!A:E,5,FALSE), "Categoria não encontrada") -> EPI | D6: =IFERROR(VLOOKUP(A6,PRODUTOS!A:E,4,FALSE), "Categoria não encontrada") -> UN | E6: =SUMIFS(MOVIMENTACOES!F:F,MOVIMENTACOES!C:C,A6,MOVIMENTACOES!E:E,"Entrada") -> 1 | F6: =SUMIFS(MOVIMENTACOES!F:F,MOVIMENTACOES!C:C,A6,MOVIMENTACOES!E:E,"Saída") -> 0 | G6: =E6-F6 -> 1 | H6: =IF(G6=0, "Faltando", IF(G6<=3, "Atenção", "OK")) -> Atenção | I6: =VLOOKUP(A6, PRODUTOS!A:H, 3, FALSE) -> SIGBP
A7: 200052481 | B7: =VLOOKUP(A7,produto,2,0) -> PROTETOR AURICULAR TIPO CONCHA | C7: =IFERROR(VLOOKUP(A7,PRODUTOS!A:E,5,FALSE), "Categoria não encontrada") -> EPI | D7: =IFERROR(VLOOKUP(A7,PRODUTOS!A:E,4,FALSE), "Categoria não encontrada") -> CX | E7: =SUMIFS(MOVIMENTACOES!F:F,MOVIMENTACOES!C:C,A7,MOVIMENTACOES!E:E,"Entrada") -> 1 | F7: =SUMIFS(MOVIMENTACOES!F:F,MOVIMENTACOES!C:C,A7,MOVIMENTACOES!E:E,"Saída") -> 0 | G7: =E7-F7 -> 1 | H7: =IF(G7=0, "Faltando", IF(G7<=3, "Atenção", "OK")) -> Atenção | I7: =VLOOKUP(A7, PRODUTOS!A:H, 3, FALSE) -> SIGBP
A8: 200000700 | B8: =VLOOKUP(A8,produto,2,0) -> TOUCA DESCARTAVEL PACOTE COM 100 UN | C8: =IFERROR(VLOOKUP(A8,PRODUTOS!A:E,5,FALSE), "Categoria não encontrada") -> EPI | D8: =IFERROR(VLOOKUP(A8,PRODUTOS!A:E,4,FALSE), "Categoria não encontrada") -> UN | E8: =SUMIFS(MOVIMENTACOES!F:F,MOVIMENTACOES!C:C,A8,MOVIMENTACOES!E:E,"Entrada") -> 1 | F8: =SUMIFS(MOVIMENTACOES!F:F,MOVIMENTACOES!C:C,A8,MOVIMENTACOES!E:E,"Saída") -> 0 | G8: =E8-F8 -> 1 | H8: =IF(G8=0, "Faltando", IF(G8<=3, "Atenção", "OK")) -> Atenção | I8: =VLOOKUP(A8, PRODUTOS!A:H, 3, FALSE) -> SIGBP
A9: 200038284 | B9: =VLOOKUP(A9,produto,2,0) -> ABRAÇADEIRA DE NYLON 100X2,5MM | C9: =IFERROR(VLOOKUP(A9,PRODUTOS!A:E,5,FALSE), "Categoria não encontrada") -> EXPEDIENTE | D9: =IFERROR(VLOOKUP(A9,PRODUTOS!A:E,4,FALSE), "Categoria não encontrada") -> UN | E9: =SUMIFS(MOVIMENTACOES!F:F,MOVIMENTACOES!C:C,A9,MOVIMENTACOES!E:E,"Entrada") -> 2 | F9: =SUMIFS(MOVIMENTACOES!F:F,MOVIMENTACOES!C:C,A9,MOVIMENTACOES!E:E,"Saída") -> 1 | G9: =E9-F9 -> 1 | H9: =IF(G9=0, "Faltando", IF(G9<=3, "Atenção", "OK")) -> Atenção | I9: =VLOOKUP(A9, PRODUTOS!A:H, 3, FALSE) -> SIGBP
A10: 200069551 | B10: =VLOOKUP(A10,produto,2,0) -> ALFINETE MARCADOR DE MAPA 8MM TIPO BOLA EM PLASTICO 50UN | C10: =IFERROR(VLOOKUP(A10,PRODUTOS!A:E,5,FALSE), "Categoria não encontrada") -> EXPEDIENTE | D10: =IFERROR(VLOOKUP(A10,PRODUTOS!A:E,4,FALSE), "Categoria não encontrada") -> CX | E10: =SUMIFS(MOVIMENTACOES!F:F,MOVIMENTACOES!C:C,A10,MOVIMENTACOES!E:E,"Entrada") -> 3 | F10: =SUMIFS(MOVIMENTACOES!F:F,MOVIMENTACOES!C:C,A10,MOVIMENTACOES!E:E,"Saída") -> 1 | G10: =E10-F10 -> 2 | H10: =IF(G10=0, "Faltando", IF(G10<=3, "Atenção", "OK")) -> Atenção | I10: =VLOOKUP(A10, PRODUTOS!A:H, 3, FALSE) -> SIGBP
A11: 200043234 | B11: =VLOOKUP(A11,produto,2,0) -> ALFINETE PARA COSTURA CABO FINO Nº29 | C11: =IFERROR(VLOOKUP(A11,PRODUTOS!A:E,5,FALSE), "Categoria não encontrada") -> EXPEDIENTE | D11: =IFERROR(VLOOKUP(A11,PRODUTOS!A:E,4,FALSE), "Categoria não encontrada") -> CX | E11: =SUMIFS(MOVIMENTACOES!F:F,MOVIMENTACOES!C:C,A11,MOVIMENTACOES!E:E,"Entrada") -> 3 | F11: =SUMIFS(MOVIMENTACOES!F:F,MOVIMENTACOES!C:C,A11,MOVIMENTACOES!E:E,"Saída") -> 0 | G11: =E11-F11 -> 3 | H11: =IF(G11=0, "Faltando", IF(G11<=3, "Atenção", "OK")) -> Atenção | I11: =VLOOKUP(A11, PRODUTOS!A:H, 3, FALSE) -> SIGBP
A12: 200040799 | B12: =VLOOKUP(A12,produto,2,0) -> CAIXA ARQUIVO MORTO EM POLIONDA MED (380X175X290) MM NA COR AMARELA | C12: =IFERROR(VLOOKUP(A12,PRODUTOS!A:E,5,FALSE), "Categoria não encontrada") -> EXPEDIENTE | D12: =IFERROR(VLOOKUP(A12,PRODUTOS!A:E,4,FALSE), "Categoria não encontrada") -> UN | E12: =SUMIFS(MOVIMENTACOES!F:F,MOVIMENTACOES!C:C,A12,MOVIMENTACOES!E:E,"Entrada") -> 4 | F12: =SUMIFS(MOVIMENTACOES!F:F,MOVIMENTACOES!C:C,A12,MOVIMENTACOES!E:E,"Saída") -> 2 | G12: =E12-F12 -> 2 | H12: =IF(G12=0, "Faltando", IF(G12<=3, "Atenção", "OK")) -> Atenção | I12: =VLOOKUP(A12, PRODUTOS!A:H, 3, FALSE) -> SIGBP
A13: 200036941 | B13: =VLOOKUP(A13,produto,2,0) -> COLA BRANCA BASTAO 10G | C13: =IFERROR(VLOOKUP(A13,PRODUTOS!A:E,5,FALSE), "Categoria não encontrada") -> EXPEDIENTE | D13: =IFERROR(VLOOKUP(A13,PRODUTOS!A:E,4,FALSE), "Categoria não encontrada") -> UN | E13: =SUMIFS(MOVIMENTACOES!F:F,MOVIMENTACOES!C:C,A13,MOVIMENTACOES!E:E,"Entrada") -> 2 | F13: =SUMIFS(MOVIMENTACOES!F:F,MOVIMENTACOES!C:C,A13,MOVIMENTACOES!E:E,"Saída") -> 0 | G13: =E13-F13 -> 2 | H13: =IF(G13=0, "Faltando", IF(G13<=3, "Atenção", "OK")) -> Atenção | I13: =VLOOKUP(A13, PRODUTOS!A:H, 3, FALSE) -> SIGBP
A14: 200036189 | B14: =VLOOKUP(A14,produto,2,0) -> COPO DESCARTAVEL 180ML | C14: =IFERROR(VLOOKUP(A14,PRODUTOS!A:E,5,FALSE), "Categoria não encontrada") -> EXPEDIENTE | D14: =IFERROR(VLOOKUP(A14,PRODUTOS!A:E,4,FALSE), "Categoria não encontrada") -> UN | E14: =SUMIFS(MOVIMENTACOES!F:F,MOVIMENTACOES!C:C,A14,MOVIMENTACOES!E:E,"Entrada") -> 43 | F14: =SUMIFS(MOVIMENTACOES!F:F,MOVIMENTACOES!C:C,A14,MOVIMENTACOES!E:E,"Saída") -> 40 | G14: =E14-F14 -> 3 | H14: =IF(G14=0, "Faltando", IF(G14<=3, "Atenção", "OK")) -> Atenção | I14: =VLOOKUP(A14, PRODUTOS!A:H, 3, FALSE) -> SIGBP
... A27: 200000408 | B27: =VLOOKUP(A27,produto,2,0) -> LENÇOL DESCARTAVEL 50 x 70 mm | C27: =IFERROR(VLOOKUP(A27,PRODUTOS!A:E,5,FALSE), "Categoria não encontrada") -> LIMPEZA | D27: =IFERROR(VLOOKUP(A27,PRODUTOS!A:E,4,FALSE), "Categoria não encontrada") -> UN | E27: =SUMIFS(MOVIMENTACOES!F:F,MOVIMENTACOES!C:C,A27,MOVIMENTACOES!E:E,"Entrada") -> 2 | F27: =SUMIFS(MOVIMENTACOES!F:F,MOVIMENTACOES!C:C,A27,MOVIMENTACOES!E:E,"Saída") -> 1 | G27: =E27-F27 -> 1 | H27: =IF(G27=0, "Faltando", IF(G27<=3, "Atenção", "OK")) -> Atenção | I27: =VLOOKUP(A27, PRODUTOS!A:H, 3, FALSE) -> SIGBP
A28: 200000019 | B28: =VLOOKUP(A28,produto,2,0) -> Papel Toalha Interfolhado | C28: =IFERROR(VLOOKUP(A28,PRODUTOS!A:E,5,FALSE), "Categoria não encontrada") -> LIMPEZA | D28: =IFERROR(VLOOKUP(A28,PRODUTOS!A:E,4,FALSE), "Categoria não encontrada") -> RL | E28: =SUMIFS(MOVIMENTACOES!F:F,MOVIMENTACOES!C:C,A28,MOVIMENTACOES!E:E,"Entrada") -> 3 | F28: =SUMIFS(MOVIMENTACOES!F:F,MOVIMENTACOES!C:C,A28,MOVIMENTACOES!E:E,"Saída") -> 0 | G28: =E28-F28 -> 3 | H28: =IF(G28=0, "Faltando", IF(G28<=3, "Atenção", "OK")) -> Atenção | I28: =VLOOKUP(A28, PRODUTOS!A:H, 3, FALSE) -> SIGBP
A29: 200070056 | B29: =VLOOKUP(A29,produto,2,0) -> PAPEL TOALHADE ROLHO | C29: =IFERROR(VLOOKUP(A29,PRODUTOS!A:E,5,FALSE), "Categoria não encontrada") -> LIMPEZA | D29: =IFERROR(VLOOKUP(A29,PRODUTOS!A:E,4,FALSE), "Categoria não encontrada") -> UN | E29: =SUMIFS(MOVIMENTACOES!F:F,MOVIMENTACOES!C:C,A29,MOVIMENTACOES!E:E,"Entrada") -> 1 | F29: =SUMIFS(MOVIMENTACOES!F:F,MOVIMENTACOES!C:C,A29,MOVIMENTACOES!E:E,"Saída") -> 0 | G29: =E29-F29 -> 1 | H29: =IF(G29=0, "Faltando", IF(G29<=3, "Atenção", "OK")) -> Atenção | I29: =VLOOKUP(A29, PRODUTOS!A:H, 3, FALSE) -> SIGBP
A30: 200061213 | B30: =VLOOKUP(A30,produto,2,0) -> SABONETE LIQUIDO CONCENTRADO 1L | C30: =IFERROR(VLOOKUP(A30,PRODUTOS!A:E,5,FALSE), "Categoria não encontrada") -> LIMPEZA | D30: =IFERROR(VLOOKUP(A30,PRODUTOS!A:E,4,FALSE), "Categoria não encontrada") -> UN | E30: =SUMIFS(MOVIMENTACOES!F:F,MOVIMENTACOES!C:C,A30,MOVIMENTACOES!E:E,"Entrada") -> 1 | F30: =SUMIFS(MOVIMENTACOES!F:F,MOVIMENTACOES!C:C,A30,MOVIMENTACOES!E:E,"Saída") -> 0 | G30: =E30-F30 -> 1 | H30: =IF(G30=0, "Faltando", IF(G30<=3, "Atenção", "OK")) -> Atenção | I30: =VLOOKUP(A30, PRODUTOS!A:H, 3, FALSE) -> SIGBP
A31: 200000054 | B31: =VLOOKUP(A31,produto,2,0) -> FITA DE BORDA 1,5 x 2,5 x 1mm | C31: =IFERROR(VLOOKUP(A31,PRODUTOS!A:E,5,FALSE), "Categoria não encontrada") -> MATERIAL T.O | D31: =IFERROR(VLOOKUP(A31,PRODUTOS!A:E,4,FALSE), "Categoria não encontrada") -> UN | E31: =SUMIFS(MOVIMENTACOES!F:F,MOVIMENTACOES!C:C,A31,MOVIMENTACOES!E:E,"Entrada") -> 5 | F31: =SUMIFS(MOVIMENTACOES!F:F,MOVIMENTACOES!C:C,A31,MOVIMENTACOES!E:E,"Saída") -> 3 | G31: =E31-F31 -> 2 | H31: =IF(G31=0, "Faltando", IF(G31<=3, "Atenção", "OK")) -> Atenção | I31: =VLOOKUP(A31, PRODUTOS!A:H, 3, FALSE) -> ARTICULATO
A32: 200000055 | B32: =VLOOKUP(A32,produto,2,0) -> PEÇA / MATERIAL PARA ORTESES tipo FORRAÇÃO AUTO-ADESIVA ESP | C32: =IFERROR(VLOOKUP(A32,PRODUTOS!A:E,5,FALSE), "Categoria não encontrada") -> MATERIAL T.O | D32: =IFERROR(VLOOKUP(A32,PRODUTOS!A:E,4,FALSE), "Categoria não encontrada") -> UN | E32: =SUMIFS(MOVIMENTACOES!F:F,MOVIMENTACOES!C:C,A32,MOVIMENTACOES!E:E,"Entrada") -> 3 | F32: =SUMIFS(MOVIMENTACOES!F:F,MOVIMENTACOES!C:C,A32,MOVIMENTACOES!E:E,"Saída") -> 1 | G32: =E32-F32 -> 2 | H32: =IF(G32=0, "Faltando", IF(G32<=3, "Atenção", "OK")) -> Atenção | I32: =VLOOKUP(A32, PRODUTOS!A:H, 3, FALSE) -> ARTICULATO
A33: 200000060 | B33: =VLOOKUP(A33,produto,2,0) -> VELCRO FEMEA 50mm VERMELHO | C33: =IFERROR(VLOOKUP(A33,PRODUTOS!A:E,5,FALSE), "Categoria não encontrada") -> MATERIAL T.O | D33: =IFERROR(VLOOKUP(A33,PRODUTOS!A:E,4,FALSE), "Categoria não encontrada") -> UN | E33: =SUMIFS(MOVIMENTACOES!F:F,MOVIMENTACOES!C:C,A33,MOVIMENTACOES!E:E,"Entrada") -> 1 | F33: =SUMIFS(MOVIMENTACOES!F:F,MOVIMENTACOES!C:C,A33,MOVIMENTACOES!E:E,"Saída") -> 0 | G33: =E33-F33 -> 1 | H33: =IF(G33=0, "Faltando", IF(G33<=3, "Atenção", "OK")) -> Atenção | I33: =VLOOKUP(A33, PRODUTOS!A:H, 3, FALSE) -> ARTICULATO
A34: 200000057 | B34: =VLOOKUP(A34,produto,2,0) -> VELCRO FEMEA 50mm AZUL MARINHO V182 | C34: =IFERROR(VLOOKUP(A34,PRODUTOS!A:E,5,FALSE), "Categoria não encontrada") -> MATERIAL T.O | D34: =IFERROR(VLOOKUP(A34,PRODUTOS!A:E,4,FALSE), "Categoria não encontrada") -> UN | E34: =SUMIFS(MOVIMENTACOES!F:F,MOVIMENTACOES!C:C,A34,MOVIMENTACOES!E:E,"Entrada") -> 2 | F34: =SUMIFS(MOVIMENTACOES!F:F,MOVIMENTACOES!C:C,A34,MOVIMENTACOES!E:E,"Saída") -> 1 | G34: =E34-F34 -> 1 | H34: =IF(G34=0, "Faltando", IF(G34<=3, "Atenção", "OK")) -> Atenção | I34: =VLOOKUP(A34, PRODUTOS!A:H, 3, FALSE) -> ARTICULATO
A35: 200000058 | B35: =VLOOKUP(A35,produto,2,0) -> VELCRO FEMEA 50mm Verde Escuro | C35: =IFERROR(VLOOKUP(A35,PRODUTOS!A:E,5,FALSE), "Categoria não encontrada") -> MATERIAL T.O | D35: =IFERROR(VLOOKUP(A35,PRODUTOS!A:E,4,FALSE), "Categoria não encontrada") -> UN | E35: =SUMIFS(MOVIMENTACOES!F:F,MOVIMENTACOES!C:C,A35,MOVIMENTACOES!E:E,"Entrada") -> 2 | F35: =SUMIFS(MOVIMENTACOES!F:F,MOVIMENTACOES!C:C,A35,MOVIMENTACOES!E:E,"Saída") -> 1 | G35: =E35-F35 -> 1 | H35: =IF(G35=0, "Faltando", IF(G35<=3, "Atenção", "OK")) -> Atenção | I35: =VLOOKUP(A35, PRODUTOS!A:H, 3, FALSE) -> ARTICULATO
A36: 200000064 | B36: =VLOOKUP(A36,produto,2,0) -> VELCRO FEMEA 50mm BEGE | C36: =IFERROR(VLOOKUP(A36,PRODUTOS!A:E,5,FALSE), "Categoria não encontrada") -> MATERIAL T.O | D36: =IFERROR(VLOOKUP(A36,PRODUTOS!A:E,4,FALSE), "Categoria não encontrada") -> UN | E36: =SUMIFS(MOVIMENTACOES!F:F,MOVIMENTACOES!C:C,A36,MOVIMENTACOES!E:E,"Entrada") -> 2 | F36: =SUMIFS(MOVIMENTACOES!F:F,MOVIMENTACOES!C:C,A36,MOVIMENTACOES!E:E,"Saída") -> 1 | G36: =E36-F36 -> 1 | H36: =IF(G36=0, "Faltando", IF(G36<=3, "Atenção", "OK")) -> Atenção | I36: =VLOOKUP(A36, PRODUTOS!A:H, 3, FALSE) -> ARTICULATO
A37: 200000062 | B37: =VLOOKUP(A37,produto,2,0) -> VELCRO FEMEA 50mm LARANJA V627 | C37: =IFERROR(VLOOKUP(A37,PRODUTOS!A:E,5,FALSE), "Categoria não encontrada") -> MATERIAL T.O | D37: =IFERROR(VLOOKUP(A37,PRODUTOS!A:E,4,FALSE), "Categoria não encontrada") -> UN | E37: =SUMIFS(MOVIMENTACOES!F:F,MOVIMENTACOES!C:C,A37,MOVIMENTACOES!E:E,"Entrada") -> 2 | F37: =SUMIFS(MOVIMENTACOES!F:F,MOVIMENTACOES!C:C,A37,MOVIMENTACOES!E:E,"Saída") -> 0 | G37: =E37-F37 -> 2 | H37: =IF(G37=0, "Faltando", IF(G37<=3, "Atenção", "OK")) -> Atenção | I37: =VLOOKUP(A37, PRODUTOS!A:H, 3, FALSE) -> ARTICULATO
A38: 200000059 | B38: =VLOOKUP(A38,produto,2,0) -> VELCRO FEMEA 50mm VINHO V328 | C38: =IFERROR(VLOOKUP(A38,PRODUTOS!A:E,5,FALSE), "Categoria não encontrada") -> MATERIAL T.O | D38: =IFERROR(VLOOKUP(A38,PRODUTOS!A:E,4,FALSE), "Categoria não encontrada") -> UN | E38: =SUMIFS(MOVIMENTACOES!F:F,MOVIMENTACOES!C:C,A38,MOVIMENTACOES!E:E,"Entrada") -> 2 | F38: =SUMIFS(MOVIMENTACOES!F:F,MOVIMENTACOES!C:C,A38,MOVIMENTACOES!E:E,"Saída") -> 1 | G38: =E38-F38 -> 1 | H38: =IF(G38=0, "Faltando", IF(G38<=3, "Atenção", "OK")) -> Atenção | I38: =VLOOKUP(A38, PRODUTOS!A:H, 3, FALSE) -> ARTICULATO
A39: 200000061 | B39: =VLOOKUP(A39,produto,2,0) -> VELCRO FEMEA 50mm AMARELO | C39: =IFERROR(VLOOKUP(A39,PRODUTOS!A:E,5,FALSE), "Categoria não encontrada") -> MATERIAL T.O | D39: =IFERROR(VLOOKUP(A39,PRODUTOS!A:E,4,FALSE), "Categoria não encontrada") -> UN | E39: =SUMIFS(MOVIMENTACOES!F:F,MOVIMENTACOES!C:C,A39,MOVIMENTACOES!E:E,"Entrada") -> 1 | F39: =SUMIFS(MOVIMENTACOES!F:F,MOVIMENTACOES!C:C,A39,MOVIMENTACOES!E:E,"Saída") -> 0 | G39: =E39-F39 -> 1 | H39: =IF(G39=0, "Faltando", IF(G39<=3, "Atenção", "OK")) -> Atenção | I39: =VLOOKUP(A39, PRODUTOS!A:H, 3, FALSE) -> ARTICULATO
A40: 200000023 | B40: =VLOOKUP(A40,produto,2,0) -> VELCRO FEMEA 50mm ROSA | C40: =IFERROR(VLOOKUP(A40,PRODUTOS!A:E,5,FALSE), "Categoria não encontrada") -> MATERIAL T.O | D40: =IFERROR(VLOOKUP(A40,PRODUTOS!A:E,4,FALSE), "Categoria não encontrada") -> UN | E40: =SUMIFS(MOVIMENTACOES!F:F,MOVIMENTACOES!C:C,A40,MOVIMENTACOES!E:E,"Entrada") -> 1 | F40: =SUMIFS(MOVIMENTACOES!F:F,MOVIMENTACOES!C:C,A40,MOVIMENTACOES!E:E,"Saída") -> 0 | G40: =E40-F40 -> 1 | H40: =IF(G40=0, "Faltando", IF(G40<=3, "Atenção", "OK")) -> Atenção | I40: =VLOOKUP(A40, PRODUTOS!A:H, 3, FALSE) -> SIGBP
A41: 200000050 | B41: =VLOOKUP(A41,produto,2,0) -> ORFICAST BLUE 300cm x 3cm FITA TERMOPLASTICA | C41: =IFERROR(VLOOKUP(A41,PRODUTOS!A:E,5,FALSE), "Categoria não encontrada") -> MATERIAL T.O | D41: =IFERROR(VLOOKUP(A41,PRODUTOS!A:E,4,FALSE), "Categoria não encontrada") -> UN | E41: =SUMIFS(MOVIMENTACOES!F:F,MOVIMENTACOES!C:C,A41,MOVIMENTACOES!E:E,"Entrada") -> 4 | F41: =SUMIFS(MOVIMENTACOES!F:F,MOVIMENTACOES!C:C,A41,MOVIMENTACOES!E:E,"Saída") -> 2 | G41: =E41-F41 -> 2 | H41: =IF(G41=0, "Faltando", IF(G41<=3, "Atenção", "OK")) -> Atenção | I41: =VLOOKUP(A41, PRODUTOS!A:H, 3, FALSE) -> EFECTIV
A42: 200000026 | B42: =VLOOKUP(A42,produto,2,0) -> PLACA TERMOPLASTICA - ORFIT ECO NATUREL 45 x 60 cm 2.4 mm | C42: =IFERROR(VLOOKUP(A42,PRODUTOS!A:E,5,FALSE), "Categoria não encontrada") -> MATERIAL T.O | D42: =IFERROR(VLOOKUP(A42,PRODUTOS!A:E,4,FALSE), "Categoria não encontrada") -> UN | E42: =SUMIFS(MOVIMENTACOES!F:F,MOVIMENTACOES!C:C,A42,MOVIMENTACOES!E:E,"Entrada") -> 7 | F42: =SUMIFS(MOVIMENTACOES!F:F,MOVIMENTACOES!C:C,A42,MOVIMENTACOES!E:E,"Saída") -> 6 | G42: =E42-F42 -> 1 | H42: =IF(G42=0, "Faltando", IF(G42<=3, "Atenção", "OK")) -> Atenção | I42: =VLOOKUP(A42, PRODUTOS!A:H, 3, FALSE) -> EFECTIV
A43: 200000098 | B43: =VLOOKUP(A43,produto,2,0) -> LAMINA SURFORM | C43: OFICINA | D43: =IFERROR(VLOOKUP(A43,PRODUTOS!A:E,4,FALSE), "Categoria não encontrada") | E43: =SUMIFS(MOVIMENTACOES!F:F,MOVIMENTACOES!C:C,A43,MOVIMENTACOES!E:E,"Entrada") -> 3 | F43: =SUMIFS(MOVIMENTACOES!F:F,MOVIMENTACOES!C:C,A43,MOVIMENTACOES!E:E,"Saída") -> 0 | G43: =E43-F43 -> 3 | H43: =IF(G43=0, "Faltando", IF(G43<=3, "Atenção", "OK")) -> Atenção | I43: =VLOOKUP(A43, PRODUTOS!A:H, 3, FALSE)
A44: 200000097 | B44: =VLOOKUP(A44,produto,2,0) -> SILICONE SPRAY 300ML | C44: =IFERROR(VLOOKUP(A44,PRODUTOS!A:E,5,FALSE), "Categoria não encontrada") -> OFICINA | D44: =IFERROR(VLOOKUP(A44,PRODUTOS!A:E,4,FALSE), "Categoria não encontrada") -> UN | E44: =SUMIFS(MOVIMENTACOES!F:F,MOVIMENTACOES!C:C,A44,MOVIMENTACOES!E:E,"Entrada") -> 6 | F44: =SUMIFS(MOVIMENTACOES!F:F,MOVIMENTACOES!C:C,A44,MOVIMENTACOES!E:E,"Saída") -> 3 | G44: =E44-F44 -> 3 | H44: =IF(G44=0, "Faltando", IF(G44<=3, "Atenção", "OK")) -> Atenção | I44: =VLOOKUP(A44, PRODUTOS!A:H, 3, FALSE) -> SIGBP
A45: 200044160 | B45: =VLOOKUP(A45,produto,2,0) -> DESENGRIPANTE SPRAY 300ML | C45: =IFERROR(VLOOKUP(A45,PRODUTOS!A:E,5,FALSE), "Categoria não encontrada") -> OFICINA | D45: =IFERROR(VLOOKUP(A45,PRODUTOS!A:E,4,FALSE), "Categoria não encontrada") -> UN | E45: =SUMIFS(MOVIMENTACOES!F:F,MOVIMENTACOES!C:C,A45,MOVIMENTACOES!E:E,"Entrada") -> 3 | F45: =SUMIFS(MOVIMENTACOES!F:F,MOVIMENTACOES!C:C,A45,MOVIMENTACOES!E:E,"Saída") -> 1 | G45: =E45-F45 -> 2 | H45: =IF(G45=0, "Faltando", IF(G45<=3, "Atenção", "OK")) -> Atenção | I45: =VLOOKUP(A45, PRODUTOS!A:H, 3, FALSE) -> SIGBP
A46: 200085970 | B46: =VLOOKUP(A46,produto,2,0) -> COLA DE CONTATO MULTIUSO DE 2,8KG | C46: =IFERROR(VLOOKUP(A46,PRODUTOS!A:E,5,FALSE), "Categoria não encontrada") -> OFICINA | D46: =IFERROR(VLOOKUP(A46,PRODUTOS!A:E,4,FALSE), "Categoria não encontrada") -> UN | E46: =SUMIFS(MOVIMENTACOES!F:F,MOVIMENTACOES!C:C,A46,MOVIMENTACOES!E:E,"Entrada") -> 12 | F46: =SUMIFS(MOVIMENTACOES!F:F,MOVIMENTACOES!C:C,A46,MOVIMENTACOES!E:E,"Saída") -> 10 | G46: =E46-F46 -> 2 | H46: =IF(G46=0, "Faltando", IF(G46<=3, "Atenção", "OK")) -> Atenção | I46: =VLOOKUP(A46, PRODUTOS!A:H, 3, FALSE) -> SIGBP
A47: 200000066 | B47: =VLOOKUP(A47,produto,2,0) -> ATADURA GESSADA 15cm x 3m, cx com 20 und | C47: =IFERROR(VLOOKUP(A47,PRODUTOS!A:E,5,FALSE), "Categoria não encontrada") -> ORTESES E PROTESES | D47: =IFERROR(VLOOKUP(A47,PRODUTOS!A:E,4,FALSE), "Categoria não encontrada") -> CX | E47: =SUMIFS(MOVIMENTACOES!F:F,MOVIMENTACOES!C:C,A47,MOVIMENTACOES!E:E,"Entrada") -> 12 | F47: =SUMIFS(MOVIMENTACOES!F:F,MOVIMENTACOES!C:C,A47,MOVIMENTACOES!E:E,"Saída") -> 9 | G47: =E47-F47 -> 3 | H47: =IF(G47=0, "Faltando", IF(G47<=3, "Atenção", "OK")) -> Atenção
A48: 200000065 | B48: =VLOOKUP(A48,produto,2,0) -> ATADURA GESSADA 20cm x 4m, cx com 20 und | C48: =IFERROR(VLOOKUP(A48,PRODUTOS!A:E,5,FALSE), "Categoria não encontrada") -> ORTESES E PROTESES | D48: =IFERROR(VLOOKUP(A48,PRODUTOS!A:E,4,FALSE), "Categoria não encontrada") -> CX | E48: =SUMIFS(MOVIMENTACOES!F:F,MOVIMENTACOES!C:C,A48,MOVIMENTACOES!E:E,"Entrada") -> 7 | F48: =SUMIFS(MOVIMENTACOES!F:F,MOVIMENTACOES!C:C,A48,MOVIMENTACOES!E:E,"Saída") -> 5 | G48: =E48-F48 -> 2 | H48: =IF(G48=0, "Faltando", IF(G48<=3, "Atenção", "OK")) -> Atenção
A49: 200000095 | B49: =VLOOKUP(A49,produto,2,0) -> ENDURECEDOR PARA RESINA | C49: =IFERROR(VLOOKUP(A49,PRODUTOS!A:E,5,FALSE), "Categoria não encontrada") -> ORTESES E PROTESES | D49: =IFERROR(VLOOKUP(A49,PRODUTOS!A:E,4,FALSE), "Categoria não encontrada") -> UN | E49: =SUMIFS(MOVIMENTACOES!F:F,MOVIMENTACOES!C:C,A49,MOVIMENTACOES!E:E,"Entrada") -> 2 | F49: =SUMIFS(MOVIMENTACOES!F:F,MOVIMENTACOES!C:C,A49,MOVIMENTACOES!E:E,"Saída") -> 1 | G49: =E49-F49 -> 1 | H49: =IF(G49=0, "Faltando", IF(G49<=3, "Atenção", "OK")) -> Atenção | I49: =VLOOKUP(A49, PRODUTOS!A:H, 3, FALSE) -> SES - Secretaria de Estado da Saude
A50: 200000091 | B50: =VLOOKUP(A50,produto,2,0) -> (MTA-20)MALHA ORTOPEDICA TUBULAR EM FIO DE ALGODÃO 20cm | C50: =IFERROR(VLOOKUP(A50,PRODUTOS!A:E,5,FALSE), "Categoria não encontrada") -> ORTESES E PROTESES | D50: =IFERROR(VLOOKUP(A50,PRODUTOS!A:E,4,FALSE), "Categoria não encontrada") -> UN | E50: =SUMIFS(MOVIMENTACOES!F:F,MOVIMENTACOES!C:C,A50,MOVIMENTACOES!E:E,"Entrada") -> 2 | F50: =SUMIFS(MOVIMENTACOES!F:F,MOVIMENTACOES!C:C,A50,MOVIMENTACOES!E:E,"Saída") -> 0 | G50: =E50-F50 -> 2 | H50: =IF(G50=0, "Faltando", IF(G50<=3, "Atenção", "OK")) -> Atenção | I50: =VLOOKUP(A50, PRODUTOS!A:H, 3, FALSE) -> SES - Secretaria de Estado da Saude
A51: 200000066 | B51: =VLOOKUP(A51,produto,2,0) -> ATADURA GESSADA 15cm x 3m, cx com 20 und | C51: =IFERROR(VLOOKUP(A51,PRODUTOS!A:E,5,FALSE), "Categoria não encontrada") -> ORTESES E PROTESES | D51: =IFERROR(VLOOKUP(A51,PRODUTOS!A:E,4,FALSE), "Categoria não encontrada") -> CX | E51: =SUMIFS(MOVIMENTACOES!F:F,MOVIMENTACOES!C:C,A51,MOVIMENTACOES!E:E,"Entrada") -> 12 | F51: =SUMIFS(MOVIMENTACOES!F:F,MOVIMENTACOES!C:C,A51,MOVIMENTACOES!E:E,"Saída") -> 9 | G51: =E51-F51 -> 3 | H51: =IF(G51=0, "Faltando", IF(G51<=3, "Atenção", "OK")) -> Atenção | I51: =VLOOKUP(A51, PRODUTOS!A:H, 3, FALSE)
A52: 200000065 | B52: =VLOOKUP(A52,produto,2,0) -> ATADURA GESSADA 20cm x 4m, cx com 20 und | C52: =IFERROR(VLOOKUP(A52,PRODUTOS!A:E,5,FALSE), "Categoria não encontrada") -> ORTESES E PROTESES | D52: =IFERROR(VLOOKUP(A52,PRODUTOS!A:E,4,FALSE), "Categoria não encontrada") -> CX | E52: =SUMIFS(MOVIMENTACOES!F:F,MOVIMENTACOES!C:C,A52,MOVIMENTACOES!E:E,"Entrada") -> 7 | F52: =SUMIFS(MOVIMENTACOES!F:F,MOVIMENTACOES!C:C,A52,MOVIMENTACOES!E:E,"Saída") -> 5 | G52: =E52-F52 -> 2 | H52: =IF(G52=0, "Faltando", IF(G52<=3, "Atenção", "OK")) -> Atenção | I52: =VLOOKUP(A52, PRODUTOS!A:H, 3, FALSE)
A53: 200000068 | B53: =VLOOKUP(A53,produto,2,0) -> COB. EVA 1,5 mm OCRE PERFUROS | C53: =IFERROR(VLOOKUP(A53,PRODUTOS!A:E,5,FALSE), "Categoria não encontrada") -> OFICINA | D53: =IFERROR(VLOOKUP(A53,PRODUTOS!A:E,4,FALSE), "Categoria não encontrada") -> UN | E53: =SUMIFS(MOVIMENTACOES!F:F,MOVIMENTACOES!C:C,A53,MOVIMENTACOES!E:E,"Entrada") -> 1 | F53: =SUMIFS(MOVIMENTACOES!F:F,MOVIMENTACOES!C:C,A53,MOVIMENTACOES!E:E,"Saída") -> 0 | G53: =E53-F53 -> 1 | H53: =IF(G53=0, "Faltando", IF(G53<=3, "Atenção", "OK")) -> Atenção | I53: =VLOOKUP(A53, PRODUTOS!A:H, 3, FALSE)
A54: 200000069 | B54: =VLOOKUP(A54,produto,2,0) -> COB. EVA 2,5 mm OCRE PERFUROS | C54: =IFERROR(VLOOKUP(A54,PRODUTOS!A:E,5,FALSE), "Categoria não encontrada") -> OFICINA | D54: =IFERROR(VLOOKUP(A54,PRODUTOS!A:E,4,FALSE), "Categoria não encontrada") -> UN | E54: =SUMIFS(MOVIMENTACOES!F:F,MOVIMENTACOES!C:C,A54,MOVIMENTACOES!E:E,"Entrada") -> 1 | F54: =SUMIFS(MOVIMENTACOES!F:F,MOVIMENTACOES!C:C,A54,MOVIMENTACOES!E:E,"Saída") -> 0 | G54: =E54-F54 -> 1 | H54: =IF(G54=0, "Faltando", IF(G54<=3, "Atenção", "OK")) -> Atenção | I54: =VLOOKUP(A54, PRODUTOS!A:H, 3, FALSE)
A55: 200000070 | B55: =VLOOKUP(A55,produto,2,0) -> COB. EVA 3 mm PERFURADA OCRE G | C55: =IFERROR(VLOOKUP(A55,PRODUTOS!A:E,5,FALSE), "Categoria não encontrada") -> OFICINA | D55: =IFERROR(VLOOKUP(A55,PRODUTOS!A:E,4,FALSE), "Categoria não encontrada") -> UN | E55: =SUMIFS(MOVIMENTACOES!F:F,MOVIMENTACOES!C:C,A55,MOVIMENTACOES!E:E,"Entrada") -> 1 | F55: =SUMIFS(MOVIMENTACOES!F:F,MOVIMENTACOES!C:C,A55,MOVIMENTACOES!E:E,"Saída") -> 0 | G55: =E55-F55 -> 1 | H55: =IF(G55=0, "Faltando", IF(G55<=3, "Atenção", "OK")) -> Atenção | I55: =VLOOKUP(A55, PRODUTOS!A:H, 3, FALSE)
A56: 200046153 | B56: =VLOOKUP(A56,produto,2,0) -> ALMOFADA DE AR PNEUMATICA COM VALVULA DE REAJUSTE | C56: =IFERROR(VLOOKUP(A56,PRODUTOS!A:E,5,FALSE), "Categoria não encontrada") -> OPM Auxiliares de Locomoção | D56: =IFERROR(VLOOKUP(A56,PRODUTOS!A:E,4,FALSE), "Categoria não encontrada") -> UN | E56: =SUMIFS(MOVIMENTACOES!F:F,MOVIMENTACOES!C:C,A56,MOVIMENTACOES!E:E,"Entrada") -> 30 | F56: =SUMIFS(MOVIMENTACOES!F:F,MOVIMENTACOES!C:C,A56,MOVIMENTACOES!E:E,"Saída") -> 27 | G56: =E56-F56 -> 3 | H56: =IF(G56=0, "Faltando", IF(G56<=3, "Atenção", "OK")) -> Atenção | I56: =VLOOKUP(A56, PRODUTOS!A:H, 3, FALSE) -> DELLAMED
A57: 031106017 | B57: =VLOOKUP(A57,produto,2,0) -> CJ PEDAL ELEVAVEL L30 MINIK V2 | C57: =IFERROR(VLOOKUP(A57,PRODUTOS!A:E,5,FALSE), "Categoria não encontrada") -> OPM Auxiliares de Locomoção | D57: =IFERROR(VLOOKUP(A57,PRODUTOS!A:E,4,FALSE), "Categoria não encontrada") -> UN | E57: =SUMIFS(MOVIMENTACOES!F:F,MOVIMENTACOES!C:C,A57,MOVIMENTACOES!E:E,"Entrada") -> 2 | F57: =SUMIFS(MOVIMENTACOES!F:F,MOVIMENTACOES!C:C,A57,MOVIMENTACOES!E:E,"Saída") -> 0 | G57: =E57-F57 -> 2 | H57: =IF(G57=0, "Faltando", IF(G57<=3, "Atenção", "OK")) -> Atenção | I57: =VLOOKUP(A57, PRODUTOS!A:H, 3, FALSE) -> ORTOBRAS
A58: 035106006 | B58: =VLOOKUP(A58,produto,2,0) -> CJ PEDAL DIR/ESQ INFANTIL K2/K3 (PAR) | C58: =IFERROR(VLOOKUP(A58,PRODUTOS!A:E,5,FALSE), "Categoria não encontrada") -> OPM Auxiliares de Locomoção | D58: =IFERROR(VLOOKUP(A58,PRODUTOS!A:E,4,FALSE), "Categoria não encontrada") -> UN | E58: =SUMIFS(MOVIMENTACOES!F:F,MOVIMENTACOES!C:C,A58,MOVIMENTACOES!E:E,"Entrada") -> 3 | F58: =SUMIFS(MOVIMENTACOES!F:F,MOVIMENTACOES!C:C,A58,MOVIMENTACOES!E:E,"Saída") -> 0 | G58: =E58-F58 -> 3 | H58: =IF(G58=0, "Faltando", IF(G58<=3, "Atenção", "OK")) -> Atenção | I58: =VLOOKUP(A58, PRODUTOS!A:H, 3, FALSE) -> ORTOBRAS
A59: 200000032 | B59: =VLOOKUP(A59,produto,2,0) -> INJETADO SOMENTE ENGATE 25 MM | C59: =IFERROR(VLOOKUP(A59,PRODUTOS!A:E,5,FALSE), "Categoria não encontrada") -> TAPEÇARIA | D59: =IFERROR(VLOOKUP(A59,PRODUTOS!A:E,4,FALSE), "Categoria não encontrada") -> UN | E59: =SUMIFS(MOVIMENTACOES!F:F,MOVIMENTACOES!C:C,A59,MOVIMENTACOES!E:E,"Entrada") -> 10 | F59: =SUMIFS(MOVIMENTACOES!F:F,MOVIMENTACOES!C:C,A59,MOVIMENTACOES!E:E,"Saída") -> 7 | G59: =E59-F59 -> 3 | H59: =IF(G59=0, "Faltando", IF(G59<=3, "Atenção", "OK")) -> Atenção | I59: =VLOOKUP(A59, PRODUTOS!A:H, 3, FALSE) -> SIGBP
A60: 200000034 | B60: =VLOOKUP(A60,produto,2,0) -> INJETADO SOMENTE ENGATE 50 MM | C60: =IFERROR(VLOOKUP(A60,PRODUTOS!A:E,5,FALSE), "Categoria não encontrada") -> TAPEÇARIA | D60: =IFERROR(VLOOKUP(A60,PRODUTOS!A:E,4,FALSE), "Categoria não encontrada") -> UN | E60: =SUMIFS(MOVIMENTACOES!F:F,MOVIMENTACOES!C:C,A60,MOVIMENTACOES!E:E,"Entrada") -> 2 | F60: =SUMIFS(MOVIMENTACOES!F:F,MOVIMENTACOES!C:C,A60,MOVIMENTACOES!E:E,"Saída") -> 0 | G60: =E60-F60 -> 2 | H60: =IF(G60=0, "Faltando", IF(G60<=3, "Atenção", "OK")) -> Atenção | I60: =VLOOKUP(A60, PRODUTOS!A:H, 3, FALSE) -> SIGBP
A61: 200006455 | B61: =VLOOKUP(A61,produto,2,0) -> TECIDO NAVALHADO ACOPLADO JAC BOREAL 1,80M | C61: =IFERROR(VLOOKUP(A61,PRODUTOS!A:E,5,FALSE), "Categoria não encontrada") -> TAPEÇARIA | D61: =IFERROR(VLOOKUP(A61,PRODUTOS!A:E,4,FALSE), "Categoria não encontrada") -> MT | E61: =SUMIFS(MOVIMENTACOES!F:F,MOVIMENTACOES!C:C,A61,MOVIMENTACOES!E:E,"Entrada") -> 1 | F61: =SUMIFS(MOVIMENTACOES!F:F,MOVIMENTACOES!C:C,A61,MOVIMENTACOES!E:E,"Saída") -> 0 | G61: =E61-F61 -> 1 | H61: =IF(G61=0, "Faltando", IF(G61<=3, "Atenção", "OK")) -> Atenção | I61: =VLOOKUP(A61, PRODUTOS!A:H, 3, FALSE) -> SÁ IRMÃOS
A62: 200000012 | B62: =VLOOKUP(A62,produto,2,0) -> Tesoura Alfaiate 4598-12 Onyx 12" Preta Mundial | C62: =IFERROR(VLOOKUP(A62,PRODUTOS!A:E,5,FALSE), "Categoria não encontrada") -> TAPEÇARIA | D62: =IFERROR(VLOOKUP(A62,PRODUTOS!A:E,4,FALSE), "Categoria não encontrada") -> UN | E62: =SUMIFS(MOVIMENTACOES!F:F,MOVIMENTACOES!C:C,A62,MOVIMENTACOES!E:E,"Entrada") -> 3 | F62: =SUMIFS(MOVIMENTACOES!F:F,MOVIMENTACOES!C:C,A62,MOVIMENTACOES!E:E,"Saída") -> 2 | G62: =E62-F62 -> 1 | H62: =IF(G62=0, "Faltando", IF(G62<=3, "Atenção", "OK")) -> Atenção | I62: =VLOOKUP(A62, PRODUTOS!A:H, 3, FALSE) -> SIGBP
A63: 200000014 | B63: =VLOOKUP(A63,produto,2,0) -> Tesoura Lister 20cm - Cooperflex Prime | C63: =IFERROR(VLOOKUP(A63,PRODUTOS!A:E,5,FALSE), "Categoria não encontrada") -> TAPEÇARIA | D63: =IFERROR(VLOOKUP(A63,PRODUTOS!A:E,4,FALSE), "Categoria não encontrada") -> UN | E63: =SUMIFS(MOVIMENTACOES!F:F,MOVIMENTACOES!C:C,A63,MOVIMENTACOES!E:E,"Entrada") -> 3 | F63: =SUMIFS(MOVIMENTACOES!F:F,MOVIMENTACOES!C:C,A63,MOVIMENTACOES!E:E,"Saída") -> 1 | G63: =E63-F63 -> 2 | H63: =IF(G63=0, "Faltando", IF(G63<=3, "Atenção", "OK")) -> Atenção | I63: =VLOOKUP(A63, PRODUTOS!A:H, 3, FALSE) -> SIGBP
A64: 200000016 | B64: =VLOOKUP(A64,produto,2,0) -> Tesoura Multiuso 990-10 Cushion Pro 10" Azul Mundial | C64: =IFERROR(VLOOKUP(A64,PRODUTOS!A:E,5,FALSE), "Categoria não encontrada") -> TAPEÇARIA | D64: =IFERROR(VLOOKUP(A64,PRODUTOS!A:E,4,FALSE), "Categoria não encontrada") -> UN | E64: =SUMIFS(MOVIMENTACOES!F:F,MOVIMENTACOES!C:C,A64,MOVIMENTACOES!E:E,"Entrada") -> 4 | F64: =SUMIFS(MOVIMENTACOES!F:F,MOVIMENTACOES!C:C,A64,MOVIMENTACOES!E:E,"Saída") -> 1 | G64: =E64-F64 -> 3 | H64: =IF(G64=0, "Faltando", IF(G64<=3, "Atenção", "OK")) -> Atenção | I64: =VLOOKUP(A64, PRODUTOS!A:H, 3, FALSE) -> SIGBP
A65: 200000013 | B65: =VLOOKUP(A65,produto,2,0) -> Tesoura Tecelão 601N-4.1/2 Ponto Vermelho 4 1/2" Preta Mundial | C65: =IFERROR(VLOOKUP(A65,PRODUTOS!A:E,5,FALSE), "Categoria não encontrada") -> TAPEÇARIA | D65: =IFERROR(VLOOKUP(A65,PRODUTOS!A:E,4,FALSE), "Categoria não encontrada") -> UN | E65: =SUMIFS(MOVIMENTACOES!F:F,MOVIMENTACOES!C:C,A65,MOVIMENTACOES!E:E,"Entrada") -> 3 | F65: =SUMIFS(MOVIMENTACOES!F:F,MOVIMENTACOES!C:C,A65,MOVIMENTACOES!E:E,"Saída") -> 2 | G65: =E65-F65 -> 1 | H65: =IF(G65=0, "Faltando", IF(G65<=3, "Atenção", "OK")) -> Atenção | I65: =VLOOKUP(A65, PRODUTOS!A:H, 3, FALSE) -> SIGBP
A66: 200000028 | B66: =VLOOKUP(A66,produto,2,0) -> Tesoura Tecelão Industrial Reta 1801 Practical 4" Mundial | C66: =IFERROR(VLOOKUP(A66,PRODUTOS!A:E,5,FALSE), "Categoria não encontrada") -> TAPEÇARIA | D66: =IFERROR(VLOOKUP(A66,PRODUTOS!A:E,4,FALSE), "Categoria não encontrada") -> UN | E66: =SUMIFS(MOVIMENTACOES!F:F,MOVIMENTACOES!C:C,A66,MOVIMENTACOES!E:E,"Entrada") -> 3 | F66: =SUMIFS(MOVIMENTACOES!F:F,MOVIMENTACOES!C:C,A66,MOVIMENTACOES!E:E,"Saída") -> 2 | G66: =E66-F66 -> 1 | H66: =IF(G66=0, "Faltando", IF(G66<=3, "Atenção", "OK")) -> Atenção | I66: =VLOOKUP(A66, PRODUTOS!A:H, 3, FALSE) -> SIGBP
A67: 200135429 | B67: =VLOOKUP(A67,produto,2,0) -> NYLON 900 PVC PRETO LARG 1.50 (RL) | C67: =IFERROR(VLOOKUP(A67,PRODUTOS!A:E,5,FALSE), "Categoria não encontrada") -> TAPEÇARIA | D67: =IFERROR(VLOOKUP(A67,PRODUTOS!A:E,4,FALSE), "Categoria não encontrada") -> UN | E67: =SUMIFS(MOVIMENTACOES!F:F,MOVIMENTACOES!C:C,A67,MOVIMENTACOES!E:E,"Entrada") -> 6 | F67: =SUMIFS(MOVIMENTACOES!F:F,MOVIMENTACOES!C:C,A67,MOVIMENTACOES!E:E,"Saída") -> 4 | G67: =E67-F67 -> 2 | H67: =IF(G67=0, "Faltando", IF(G67<=3, "Atenção", "OK")) -> Atenção | I67: =VLOOKUP(A67, PRODUTOS!A:H, 3, FALSE) -> (PK)RAFAEL LIMA
A68: 200000006 | B68: =VLOOKUP(A68,produto,2,0) -> OLEO MINERAL 70PS | C68: =IFERROR(VLOOKUP(A68,PRODUTOS!A:E,5,FALSE), "Categoria não encontrada") -> CONSUMO | D68: =IFERROR(VLOOKUP(A68,PRODUTOS!A:E,4,FALSE), "Categoria não encontrada") -> UN | E68: =SUMIFS(MOVIMENTACOES!F:F,MOVIMENTACOES!C:C,A68,MOVIMENTACOES!E:E,"Entrada") -> 1 | F68: =SUMIFS(MOVIMENTACOES!F:F,MOVIMENTACOES!C:C,A68,MOVIMENTACOES!E:E,"Saída") -> 1 | G68: =E68-F68 -> 0 | H68: =IF(G68=0, "Faltando", IF(G68<=3, "Atenção", "OK")) -> Faltando | I68: =VLOOKUP(A68, PRODUTOS!A:H, 3, FALSE) -> CASASLEO
A69: 200036752 | B69: =VLOOKUP(A69,produto,2,0) -> ALCOOL 1LT | C69: =IFERROR(VLOOKUP(A69,PRODUTOS!A:E,5,FALSE), "Categoria não encontrada") -> EXPEDIENTE | D69: =IFERROR(VLOOKUP(A69,PRODUTOS!A:E,4,FALSE), "Categoria não encontrada") -> UN | E69: =SUMIFS(MOVIMENTACOES!F:F,MOVIMENTACOES!C:C,A69,MOVIMENTACOES!E:E,"Entrada") -> 13 | F69: =SUMIFS(MOVIMENTACOES!F:F,MOVIMENTACOES!C:C,A69,MOVIMENTACOES!E:E,"Saída") -> 13 | G69: =E69-F69 -> 0 | H69: =IF(G69=0, "Faltando", IF(G69<=3, "Atenção", "OK")) -> Faltando | I69: =VLOOKUP(A69, PRODUTOS!A:H, 3, FALSE) -> SIGBP
A70: 200056827 | B70: =VLOOKUP(A70,produto,2,0) -> BORRACHA ESCOLAR BRANCA 34X23X8 | C70: =IFERROR(VLOOKUP(A70,PRODUTOS!A:E,5,FALSE), "Categoria não encontrada") -> EXPEDIENTE | D70: =IFERROR(VLOOKUP(A70,PRODUTOS!A:E,4,FALSE), "Categoria não encontrada") -> UN | E70: =SUMIFS(MOVIMENTACOES!F:F,MOVIMENTACOES!C:C,A70,MOVIMENTACOES!E:E,"Entrada") -> 4 | F70: =SUMIFS(MOVIMENTACOES!F:F,MOVIMENTACOES!C:C,A70,MOVIMENTACOES!E:E,"Saída") -> 4 | G70: =E70-F70 -> 0 | H70: =IF(G70=0, "Faltando", IF(G70<=3, "Atenção", "OK")) -> Faltando | I70: =VLOOKUP(A70, PRODUTOS!A:H, 3, FALSE) -> SIGBP
A71: 200041824 | B71: =VLOOKUP(A71,produto,2,0) -> ELASTICOS AMARELO | C71: =IFERROR(VLOOKUP(A71,PRODUTOS!A:E,5,FALSE), "Categoria não encontrada") -> EXPEDIENTE | D71: =IFERROR(VLOOKUP(A71,PRODUTOS!A:E,4,FALSE), "Categoria não encontrada") -> PCT | E71: 2 | F71: =SUMIFS(MOVIMENTACOES!F:F,MOVIMENTACOES!C:C,A71,MOVIMENTACOES!E:E,"Saída") -> 2 | G71: =E71-F71 -> 0 | H71: =IF(G71=0, "Faltando", IF(G71<=3, "Atenção", "OK")) -> Faltando | I71: =VLOOKUP(A71, PRODUTOS!A:H, 3, FALSE) -> SIGBP
A72: 200036618 | B72: =VLOOKUP(A72,produto,2,0) -> ESPONJA SINTETICA DUPLA FACE 10X7X2 | C72: =IFERROR(VLOOKUP(A72,PRODUTOS!A:E,5,FALSE), "Categoria não encontrada") -> EXPEDIENTE | D72: =IFERROR(VLOOKUP(A72,PRODUTOS!A:E,4,FALSE), "Categoria não encontrada") -> UN | E72: =SUMIFS(MOVIMENTACOES!F:F,MOVIMENTACOES!C:C,A72,MOVIMENTACOES!E:E,"Entrada") -> 7 | F72: =SUMIFS(MOVIMENTACOES!F:F,MOVIMENTACOES!C:C,A72,MOVIMENTACOES!E:E,"Saída") -> 7 | G72: =E72-F72 -> 0 | H72: =IF(G72=0, "Faltando", IF(G72<=3, "Atenção", "OK")) -> Faltando | I72: =VLOOKUP(A72, PRODUTOS!A:H, 3, FALSE) -> SIGBP
A73: 200054364 | B73: =VLOOKUP(A73,produto,2,0) -> ESTILETE PLASTICO DE 13CM LAMINA LARGA | C73: =IFERROR(VLOOKUP(A73,PRODUTOS!A:E,5,FALSE), "Categoria não encontrada") -> EXPEDIENTE | D73: =IFERROR(VLOOKUP(A73,PRODUTOS!A:E,4,FALSE), "Categoria não encontrada") -> UN | E73: =SUMIFS(MOVIMENTACOES!F:F,MOVIMENTACOES!C:C,A73,MOVIMENTACOES!E:E,"Entrada") -> 3 | F73: =SUMIFS(MOVIMENTACOES!F:F,MOVIMENTACOES!C:C,A73,MOVIMENTACOES!E:E,"Saída") -> 3 | G73: =E73-F73 -> 0 | H73: =IF(G73=0, "Faltando", IF(G73<=3, "Atenção", "OK")) -> Faltando | I73: =VLOOKUP(A73, PRODUTOS!A:H, 3, FALSE) -> SIGBP
A74: 200036656 | B74: =VLOOKUP(A74,produto,2,0) -> FITA ADESIVA TRANSPARENTE 45MM X 50M | C74: =IFERROR(VLOOKUP(A74,PRODUTOS!A:E,5,FALSE), "Categoria não encontrada") -> EXPEDIENTE | D74: =IFERROR(VLOOKUP(A74,PRODUTOS!A:E,4,FALSE), "Categoria não encontrada") -> UN | E74: =SUMIFS(MOVIMENTACOES!F:F,MOVIMENTACOES!C:C,A74,MOVIMENTACOES!E:E,"Entrada") -> 12 | F74: =SUMIFS(MOVIMENTACOES!F:F,MOVIMENTACOES!C:C,A74,MOVIMENTACOES!E:E,"Saída") -> 12 | G74: =E74-F74 -> 0 | H74: =IF(G74=0, "Faltando", IF(G74<=3, "Atenção", "OK")) -> Faltando | I74: =VLOOKUP(A74, PRODUTOS!A:H, 3, FALSE) -> SIGBP
A75: 200036416 | B75: =VLOOKUP(A75,produto,2,0) -> COLA BRANCA PVA EMBALAGEM DE 1KG | C75: =IFERROR(VLOOKUP(A75,PRODUTOS!A:E,5,FALSE), "Categoria não encontrada") -> EXPEDIENTE | D75: =IFERROR(VLOOKUP(A75,PRODUTOS!A:E,4,FALSE), "Categoria não encontrada") -> UN | E75: =SUMIFS(MOVIMENTACOES!F:F,MOVIMENTACOES!C:C,A75,MOVIMENTACOES!E:E,"Entrada") -> 1 | F75: =SUMIFS(MOVIMENTACOES!F:F,MOVIMENTACOES!C:C,A75,MOVIMENTACOES!E:E,"Saída") -> 1 | G75: =E75-F75 -> 0 | H75: =IF(G75=0, "Faltando", IF(G75<=3, "Atenção", "OK")) -> Faltando | I75: =VLOOKUP(A75, PRODUTOS!A:H, 3, FALSE) -> SIGBP
A76: 200052793 | B76: =VLOOKUP(A76,produto,2,0) -> CORRETIVO EM FITA 5MMX12M | C76: =IFERROR(VLOOKUP(A76,PRODUTOS!A:E,5,FALSE), "Categoria não encontrada") -> EXPEDIENTE | D76: =IFERROR(VLOOKUP(A76,PRODUTOS!A:E,4,FALSE), "Categoria não encontrada") -> UN | E76: =SUMIFS(MOVIMENTACOES!F:F,MOVIMENTACOES!C:C,A76,MOVIMENTACOES!E:E,"Entrada") -> 3 | F76: =SUMIFS(MOVIMENTACOES!F:F,MOVIMENTACOES!C:C,A76,MOVIMENTACOES!E:E,"Saída") -> 3 | G76: =E76-F76 -> 0 | H76: =IF(G76=0, "Faltando", IF(G76<=3, "Atenção", "OK")) -> Faltando | I76: =VLOOKUP(A76, PRODUTOS!A:H, 3, FALSE) -> SIGBP
A77: 200036673 | B77: =VLOOKUP(A77,produto,2,0) -> LIVRO ATA COM 200 FOLHAS NUMERADAS | C77: =IFERROR(VLOOKUP(A77,PRODUTOS!A:E,5,FALSE), "Categoria não encontrada") -> EXPEDIENTE | D77: =IFERROR(VLOOKUP(A77,PRODUTOS!A:E,4,FALSE), "Categoria não encontrada") -> UN | E77: =SUMIFS(MOVIMENTACOES!F:F,MOVIMENTACOES!C:C,A77,MOVIMENTACOES!E:E,"Entrada") -> 1 | F77: =SUMIFS(MOVIMENTACOES!F:F,MOVIMENTACOES!C:C,A77,MOVIMENTACOES!E:E,"Saída") -> 1 | G77: =E77-F77 -> 0 | H77: =IF(G77=0, "Faltando", IF(G77<=3, "Atenção", "OK")) -> Faltando | I77: =VLOOKUP(A77, PRODUTOS!A:H, 3, FALSE) -> SIGBP
A78: 200031707 | B78: =VLOOKUP(A78,produto,2,0) -> MARCA TEXTO AZUL | C78: =IFERROR(VLOOKUP(A78,PRODUTOS!A:E,5,FALSE), "Categoria não encontrada") -> EXPEDIENTE | D78: =IFERROR(VLOOKUP(A78,PRODUTOS!A:E,4,FALSE), "Categoria não encontrada") -> UN | E78: =SUMIFS(MOVIMENTACOES!F:F,MOVIMENTACOES!C:C,A78,MOVIMENTACOES!E:E,"Entrada") -> 1 | F78: =SUMIFS(MOVIMENTACOES!F:F,MOVIMENTACOES!C:C,A78,MOVIMENTACOES!E:E,"Saída") -> 1 | G78: =E78-F78 -> 0 | H78: =IF(G78=0, "Faltando", IF(G78<=3, "Atenção", "OK")) -> Faltando | I78: =VLOOKUP(A78, PRODUTOS!A:H, 3, FALSE) -> SIGBP
A79: 200052513 | B79: =VLOOKUP(A79,produto,2,0) -> PRANCHETA EM MADEIRA 33X23CM | C79: =IFERROR(VLOOKUP(A79,PRODUTOS!A:E,5,FALSE), "Categoria não encontrada") -> EXPEDIENTE | D79: =IFERROR(VLOOKUP(A79,PRODUTOS!A:E,4,FALSE), "Categoria não encontrada") -> UN | E79: =SUMIFS(MOVIMENTACOES!F:F,MOVIMENTACOES!C:C,A79,MOVIMENTACOES!E:E,"Entrada") -> 2 | F79: =SUMIFS(MOVIMENTACOES!F:F,MOVIMENTACOES!C:C,A79,MOVIMENTACOES!E:E,"Saída") -> 2 | G79: =E79-F79 -> 0 | H79: =IF(G79=0, "Faltando", IF(G79<=3, "Atenção", "OK")) -> Faltando | I79: =VLOOKUP(A79, PRODUTOS!A:H, 3, FALSE) -> SIGBP
A80: 200066236 | B80: =VLOOKUP(A80,produto,2,0) -> ENVELOPE MADEIRA A4 240 X 340MM 80G | C80: =IFERROR(VLOOKUP(A80,PRODUTOS!A:E,5,FALSE), "Categoria não encontrada") -> EXPEDIENTE | D80: =IFERROR(VLOOKUP(A80,PRODUTOS!A:E,4,FALSE), "Categoria não encontrada") -> UN | E80: =SUMIFS(MOVIMENTACOES!F:F,MOVIMENTACOES!C:C,A80,MOVIMENTACOES!E:E,"Entrada") -> 13 | F80: =SUMIFS(MOVIMENTACOES!F:F,MOVIMENTACOES!C:C,A80,MOVIMENTACOES!E:E,"Saída") -> 13 | G80: =E80-F80 -> 0 | H80: =IF(G80=0, "Faltando", IF(G80<=3, "Atenção", "OK")) -> Faltando | I80: =VLOOKUP(A80, PRODUTOS!A:H, 3, FALSE) -> SIGBP
A81: 200043839 | B81: =VLOOKUP(A81,produto,2,0) -> PASTA POLIONDA COM ABA E ELASTICO 34X25X55MM | C81: =IFERROR(VLOOKUP(A81,PRODUTOS!A:E,5,FALSE), "Categoria não encontrada") -> EXPEDIENTE | D81: =IFERROR(VLOOKUP(A81,PRODUTOS!A:E,4,FALSE), "Categoria não encontrada") -> UN | E81: =SUMIFS(MOVIMENTACOES!F:F,MOVIMENTACOES!C:C,A81,MOVIMENTACOES!E:E,"Entrada") -> 13 | F81: =SUMIFS(MOVIMENTACOES!F:F,MOVIMENTACOES!C:C,A81,MOVIMENTACOES!E:E,"Saída") -> 13 | G81: =E81-F81 -> 0 | H81: =IF(G81=0, "Faltando", IF(G81<=3, "Atenção", "OK")) -> Faltando | I81: =VLOOKUP(A81, PRODUTOS!A:H, 3, FALSE) -> SIGBP
A82: 200036530 | B82: =VLOOKUP(A82,produto,2,0) -> ODORIZADOR DE AMBIENTE AEROSOL DE 400ML | C82: =IFERROR(VLOOKUP(A82,PRODUTOS!A:E,5,FALSE), "Categoria não encontrada") -> LIMPEZA | D82: =IFERROR(VLOOKUP(A82,PRODUTOS!A:E,4,FALSE), "Categoria não encontrada") -> UN | E82: =SUMIFS(MOVIMENTACOES!F:F,MOVIMENTACOES!C:C,A82,MOVIMENTACOES!E:E,"Entrada") -> 1 | F82: =SUMIFS(MOVIMENTACOES!F:F,MOVIMENTACOES!C:C,A82,MOVIMENTACOES!E:E,"Saída") -> 1 | G82: =E82-F82 -> 0 | H82: =IF(G82=0, "Faltando", IF(G82<=3, "Atenção", "OK")) -> Faltando | I82: =VLOOKUP(A82, PRODUTOS!A:H, 3, FALSE) -> SIGBP
A83: 200000022 | B83: =VLOOKUP(A83,produto,2,0) -> VELCRO FEMEA 50mm AZUL R V443 | C83: =IFERROR(VLOOKUP(A83,PRODUTOS!A:E,5,FALSE), "Categoria não encontrada") -> MATERIAL T.O | D83: =IFERROR(VLOOKUP(A83,PRODUTOS!A:E,4,FALSE), "Categoria não encontrada") -> UN | E83: =SUMIFS(MOVIMENTACOES!F:F,MOVIMENTACOES!C:C,A83,MOVIMENTACOES!E:E,"Entrada") -> 1 | F83: =SUMIFS(MOVIMENTACOES!F:F,MOVIMENTACOES!C:C,A83,MOVIMENTACOES!E:E,"Saída") -> 1 | G83: =E83-F83 -> 0 | H83: =IF(G83=0, "Faltando", IF(G83<=3, "Atenção", "OK")) -> Faltando | I83: =VLOOKUP(A83, PRODUTOS!A:H, 3, FALSE) -> SIGBP
... A92: 200086234 | B92: =VLOOKUP(A92,produto,2,0) -> PAQUIMETRO PALSTICO | C92: =IFERROR(VLOOKUP(A92,PRODUTOS!A:E,5,FALSE), "Categoria não encontrada") -> OFICINA | D92: =IFERROR(VLOOKUP(A92,PRODUTOS!A:E,4,FALSE), "Categoria não encontrada") -> UN | E92: =SUMIFS(MOVIMENTACOES!F:F,MOVIMENTACOES!C:C,A92,MOVIMENTACOES!E:E,"Entrada") -> 2 | F92: =SUMIFS(MOVIMENTACOES!F:F,MOVIMENTACOES!C:C,A92,MOVIMENTACOES!E:E,"Saída") -> 2 | G92: =E92-F92 -> 0 | H92: =IF(G92=0, "Faltando", IF(G92<=3, "Atenção", "OK")) -> Faltando | I92: =VLOOKUP(A92, PRODUTOS!A:H, 3, FALSE) -> SIGBP
A93: 200000041 | B93: =VLOOKUP(A93,produto,2,0) -> ATADURA GESSADA 20cm x 3m, cx com 20 und | C93: =IFERROR(VLOOKUP(A93,PRODUTOS!A:E,5,FALSE), "Categoria não encontrada") -> ORTESES E PROTESES | D93: =IFERROR(VLOOKUP(A93,PRODUTOS!A:E,4,FALSE), "Categoria não encontrada") -> CX | E93: =SUMIFS(MOVIMENTACOES!F:F,MOVIMENTACOES!C:C,A93,MOVIMENTACOES!E:E,"Entrada") -> 1 | F93: =SUMIFS(MOVIMENTACOES!F:F,MOVIMENTACOES!C:C,A93,MOVIMENTACOES!E:E,"Saída") -> 1 | G93: =E93-F93 -> 0 | H93: =IF(G93=0, "Faltando", IF(G93<=3, "Atenção", "OK")) -> Faltando | I93: NÃO INFORMADO
A94: 200000096 | B94: =VLOOKUP(A94,produto,2,0) -> RESINA RIGIDA PARA LAMINAÇÃO | C94: =IFERROR(VLOOKUP(A94,PRODUTOS!A:E,5,FALSE), "Categoria não encontrada") -> ORTESES E PROTESES | D94: =IFERROR(VLOOKUP(A94,PRODUTOS!A:E,4,FALSE), "Categoria não encontrada") -> UN | E94: =SUMIFS(MOVIMENTACOES!F:F,MOVIMENTACOES!C:C,A94,MOVIMENTACOES!E:E,"Entrada") -> 2 | F94: =SUMIFS(MOVIMENTACOES!F:F,MOVIMENTACOES!C:C,A94,MOVIMENTACOES!E:E,"Saída") -> 2 | G94: =E94-F94 -> 0 | H94: =IF(G94=0, "Faltando", IF(G94<=3, "Atenção", "OK")) -> Faltando | I94: =VLOOKUP(A94, PRODUTOS!A:H, 3, FALSE) -> SES - Secretaria de Estado da Saude
A95: 200000076 | B95: =VLOOKUP(A95,produto,2,0) -> Courvin Sintetico Reforçado C/ Nylon - Cor Bege | C95: =IFERROR(VLOOKUP(A95,PRODUTOS!A:E,5,FALSE), "Categoria não encontrada") -> OFICINA | D95: =IFERROR(VLOOKUP(A95,PRODUTOS!A:E,4,FALSE), "Categoria não encontrada") -> UN | E95: =SUMIFS(MOVIMENTACOES!F:F,MOVIMENTACOES!C:C,A95,MOVIMENTACOES!E:E,"Entrada") -> 5 | F95: =SUMIFS(MOVIMENTACOES!F:F,MOVIMENTACOES!C:C,A95,MOVIMENTACOES!E:E,"Saída") -> 5 | G95: =E95-F95 -> 0 | H95: =IF(G95=0, "Faltando", IF(G95<=3, "Atenção", "OK")) -> Faltando | I95: =VLOOKUP(A95, PRODUTOS!A:H, 3, FALSE)
A96: 499106017 | B96: =VLOOKUP(A96,produto,2,0) -> CJ PEDAL ELEV. ADULTO DIR. K2/K3 | C96: =IFERROR(VLOOKUP(A96,PRODUTOS!A:E,5,FALSE), "Categoria não encontrada") -> OPM Auxiliares de Locomoção | D96: =IFERROR(VLOOKUP(A96,PRODUTOS!A:E,4,FALSE), "Categoria não encontrada") -> UN | E96: =SUMIFS(MOVIMENTACOES!F:F,MOVIMENTACOES!C:C,A96,MOVIMENTACOES!E:E,"Entrada") -> 0 | F96: =SUMIFS(MOVIMENTACOES!F:F,MOVIMENTACOES!C:C,A96,MOVIMENTACOES!E:E,"Saída") -> 0 | G96: =E96-F96 -> 0 | H96: =IF(G96=0, "Faltando", IF(G96<=3, "Atenção", "OK")) -> Faltando | I96: =VLOOKUP(A96, PRODUTOS!A:H, 3, FALSE) -> ORTOBRAS
A97: 499106018 | B97: =VLOOKUP(A97,produto,2,0) -> CJ PEDAL ELEV. ADULTO ESQ. K2/K3 | C97: =IFERROR(VLOOKUP(A97,PRODUTOS!A:E,5,FALSE), "Categoria não encontrada") -> OPM Auxiliares de Locomoção | D97: =IFERROR(VLOOKUP(A97,PRODUTOS!A:E,4,FALSE), "Categoria não encontrada") -> UN | E97: =SUMIFS(MOVIMENTACOES!F:F,MOVIMENTACOES!C:C,A97,MOVIMENTACOES!E:E,"Entrada") -> 0 | F97: =SUMIFS(MOVIMENTACOES!F:F,MOVIMENTACOES!C:C,A97,MOVIMENTACOES!E:E,"Saída") -> 0 | G97: =E97-F97 -> 0 | H97: =IF(G97=0, "Faltando", IF(G97<=3, "Atenção", "OK")) -> Faltando | I97: =VLOOKUP(A97, PRODUTOS!A:H, 3, FALSE) -> ORTOBRAS
A98: 011109001 | B98: =VLOOKUP(A98,produto,2,0) -> CJ APOIO CABECA L33 AI | C98: =IFERROR(VLOOKUP(A98,PRODUTOS!A:E,5,FALSE), "Categoria não encontrada") -> OPM Auxiliares de Locomoção | D98: =IFERROR(VLOOKUP(A98,PRODUTOS!A:E,4,FALSE), "Categoria não encontrada") -> UN | E98: =SUMIFS(MOVIMENTACOES!F:F,MOVIMENTACOES!C:C,A98,MOVIMENTACOES!E:E,"Entrada") -> 1 | F98: =SUMIFS(MOVIMENTACOES!F:F,MOVIMENTACOES!C:C,A98,MOVIMENTACOES!E:E,"Saída") -> 1 | G98: =E98-F98 -> 0 | H98: =IF(G98=0, "Faltando", IF(G98<=3, "Atenção", "OK")) -> Faltando | I98: =VLOOKUP(A98, PRODUTOS!A:H, 3, FALSE) -> ORTOBRAS
A99: 200000017 | B99: =VLOOKUP(A99,produto,2,0) -> TESOURA USO GERAL 8,0 | C99: =IFERROR(VLOOKUP(A99,PRODUTOS!A:E,5,FALSE), "Categoria não encontrada") -> TAPEÇARIA | D99: =IFERROR(VLOOKUP(A99,PRODUTOS!A:E,4,FALSE), "Categoria não encontrada") -> UN | E99: =SUMIFS(MOVIMENTACOES!F:F,MOVIMENTACOES!C:C,A99,MOVIMENTACOES!E:E,"Entrada") -> 2 | F99: =SUMIFS(MOVIMENTACOES!F:F,MOVIMENTACOES!C:C,A99,MOVIMENTACOES!E:E,"Saída") -> 2 | G99: =E99-F99 -> 0 | H99: =IF(G99=0, "Faltando", IF(G99<=3, "Atenção", "OK")) -> Faltando | I99: =VLOOKUP(A99, PRODUTOS!A:H, 3, FALSE) -> SIGBP
A100: 200000015 | B100: =VLOOKUP(A100,produto,2,0) -> Tesoura de Costura Industrial Reforçada 1470-8 Practical 8" Cinza Mundial | C100: =IFERROR(VLOOKUP(A100,PRODUTOS!A:E,5,FALSE), "Categoria não encontrada") -> TAPEÇARIA | D100: =IFERROR(VLOOKUP(A100,PRODUTOS!A:E,4,FALSE), "Categoria não encontrada") -> UN | E100: =SUMIFS(MOVIMENTACOES!F:F,MOVIMENTACOES!C:C,A100,MOVIMENTACOES!E:E,"Entrada") -> 3 | F100: =SUMIFS(MOVIMENTACOES!F:F,MOVIMENTACOES!C:C,A100,MOVIMENTACOES!E:E,"Saída") -> 3 | G100: =E100-F100 -> 0 | H100: =IF(G100=0, "Faltando", IF(G100<=3, "Atenção", "OK")) -> Faltando | I100: =VLOOKUP(A100, PRODUTOS!A:H, 3, FALSE) -> SIGBP
A101: 200037867 | B101: =VLOOKUP(A101,produto,2,0) -> TESOURA MULTIUSO CABO PLASTICO LAMINA EM AÇO INOX 21CM | C101: =IFERROR(VLOOKUP(A101,PRODUTOS!A:E,5,FALSE), "Categoria não encontrada") -> TAPEÇARIA | D101: =IFERROR(VLOOKUP(A101,PRODUTOS!A:E,4,FALSE), "Categoria não encontrada") -> UN | E101: =SUMIFS(MOVIMENTACOES!F:F,MOVIMENTACOES!C:C,A101,MOVIMENTACOES!E:E,"Entrada") -> 1 | F101: =SUMIFS(MOVIMENTACOES!F:F,MOVIMENTACOES!C:C,A101,MOVIMENTACOES!E:E,"Saída") -> 1 | G101: =E101-F101 -> 0 | H101: =IF(G101=0, "Faltando", IF(G101<=3, "Atenção", "OK")) -> Faltando | I101: =VLOOKUP(A101, PRODUTOS!A:H, 3, FALSE) -> SIGBP
A102: 200000001 | B102: =VLOOKUP(A102,produto,2,0) -> LIXA D'AGUA 150 | C102: =IFERROR(VLOOKUP(A102,PRODUTOS!A:E,5,FALSE), "Categoria não encontrada") -> CONSUMO | D102: =IFERROR(VLOOKUP(A102,PRODUTOS!A:E,4,FALSE), "Categoria não encontrada") -> UN | E102: =SUMIFS(MOVIMENTACOES!F:F,MOVIMENTACOES!C:C,A102,MOVIMENTACOES!E:E,"Entrada") -> 400 | F102: =SUMIFS(MOVIMENTACOES!F:F,MOVIMENTACOES!C:C,A102,MOVIMENTACOES!E:E,"Saída") -> 150 | G102: =E102-F102 -> 250 | H102: =IF(G102=0, "Faltando", IF(G102<=3, "Atenção", "OK")) -> OK | I102: =VLOOKUP(A102, PRODUTOS!A:H, 3, FALSE) -> CORDEIRO MAQUINAS E FERRAMENTAS
A103: 200007285 | B103: =VLOOKUP(A103,produto,2,0) -> LIXA D'MADEIRA 120 | C103: =IFERROR(VLOOKUP(A103,PRODUTOS!A:E,5,FALSE), "Categoria não encontrada") -> CONSUMO | D103: =IFERROR(VLOOKUP(A103,PRODUTOS!A:E,4,FALSE), "Categoria não encontrada") -> UN | E103: =SUMIFS(MOVIMENTACOES!F:F,MOVIMENTACOES!C:C,A103,MOVIMENTACOES!E:E,"Entrada") -> 350 | F103: =SUMIFS(MOVIMENTACOES!F:F,MOVIMENTACOES!C:C,A103,MOVIMENTACOES!E:E,"Saída") -> 100 | G103: =E103-F103 -> 250 | H103: =IF(G103=0, "Faltando", IF(G103<=3, "Atenção", "OK")) -> OK | I103: =VLOOKUP(A103, PRODUTOS!A:H, 3, FALSE) -> CORDEIRO MAQUINAS E FERRAMENTAS
A104: 200002700 | B104: =VLOOKUP(A104,produto,2,0) -> THINNER / LIMPEZA E ACABAMENTO 900ML | C104: =IFERROR(VLOOKUP(A104,PRODUTOS!A:E,5,FALSE), "Categoria não encontrada") -> CONSUMO | D104: =IFERROR(VLOOKUP(A104,PRODUTOS!A:E,4,FALSE), "Categoria não encontrada") -> UN | E104: =SUMIFS(MOVIMENTACOES!F:F,MOVIMENTACOES!C:C,A104,MOVIMENTACOES!E:E,"Entrada") -> 50 | F104: =SUMIFS(MOVIMENTACOES!F:F,MOVIMENTACOES!C:C,A104,MOVIMENTACOES!E:E,"Saída") -> 3 | G104: =E104-F104 -> 47 | H104: =IF(G104=0, "Faltando", IF(G104<=3, "Atenção", "OK")) -> OK | I104: =VLOOKUP(A104, PRODUTOS!A:H, 3, FALSE) -> CORDEIRO MAQUINAS E FERRAMENTAS
A105: 200026827 | B105: =VLOOKUP(A105,produto,2,0) -> TRINCHA 3 | C105: =IFERROR(VLOOKUP(A105,PRODUTOS!A:E,5,FALSE), "Categoria não encontrada") -> CONSUMO | D105: =IFERROR(VLOOKUP(A105,PRODUTOS!A:E,4,FALSE), "Categoria não encontrada") -> UN | E105: =SUMIFS(MOVIMENTACOES!F:F,MOVIMENTACOES!C:C,A105,MOVIMENTACOES!E:E,"Entrada") -> 50 | F105: =SUMIFS(MOVIMENTACOES!F:F,MOVIMENTACOES!C:C,A105,MOVIMENTACOES!E:E,"Saída") -> 3 | G105: =E105-F105 -> 47 | H105: =IF(G105=0, "Faltando", IF(G105<=3, "Atenção", "OK")) -> OK | I105: =VLOOKUP(A105, PRODUTOS!A:H, 3, FALSE) -> CORDEIRO MAQUINAS E FERRAMENTAS
A106: 200024290 | B106: =VLOOKUP(A106,produto,2,0) -> TRINCHA 3/4 | C106: =IFERROR(VLOOKUP(A106,PRODUTOS!A:E,5,FALSE), "Categoria não encontrada") -> CONSUMO | D106: =IFERROR(VLOOKUP(A106,PRODUTOS!A:E,4,FALSE), "Categoria não encontrada") -> UN | E106: =SUMIFS(MOVIMENTACOES!F:F,MOVIMENTACOES!C:C,A106,MOVIMENTACOES!E:E,"Entrada") -> 100 | F106: =SUMIFS(MOVIMENTACOES!F:F,MOVIMENTACOES!C:C,A106,MOVIMENTACOES!E:E,"Saída") -> 10 | G106: =E106-F106 -> 90 | H106: =IF(G106=0, "Faltando", IF(G106<=3, "Atenção", "OK")) -> OK | I106: =VLOOKUP(A106, PRODUTOS!A:H, 3, FALSE) -> CORDEIRO MAQUINAS E FERRAMENTAS
A107: 207218574 | B107: =VLOOKUP(A107,produto,2,0) -> LUVA EPI ALGODÃO MALHA PIGMENTADA PRETA | C107: =IFERROR(VLOOKUP(A107,PRODUTOS!A:E,5,FALSE), "Categoria não encontrada") -> EPI | D107: =IFERROR(VLOOKUP(A107,PRODUTOS!A:E,4,FALSE), "Categoria não encontrada") -> UN | E107: =SUMIFS(MOVIMENTACOES!F:F,MOVIMENTACOES!C:C,A107,MOVIMENTACOES!E:E,"Entrada") -> 8 | F107: =SUMIFS(MOVIMENTACOES!F:F,MOVIMENTACOES!C:C,A107,MOVIMENTACOES!E:E,"Saída") -> 1 | G107: =E107-F107 -> 7 | H107: =IF(G107=0, "Faltando", IF(G107<=3, "Atenção", "OK")) -> OK | I107: =VLOOKUP(A107, PRODUTOS!A:H, 3, FALSE) -> SIGBP
A108: 200076172 | B108: =VLOOKUP(A108,produto,2,0) -> LUVA DE VINIL G(9) COM 100 UND | C108: =IFERROR(VLOOKUP(A108,PRODUTOS!A:E,5,FALSE), "Categoria não encontrada") -> EPI | D108: =IFERROR(VLOOKUP(A108,PRODUTOS!A:E,4,FALSE), "Categoria não encontrada") -> UN | E108: =SUMIFS(MOVIMENTACOES!F:F,MOVIMENTACOES!C:C,A108,MOVIMENTACOES!E:E,"Entrada") -> 7 | F108: =SUMIFS(MOVIMENTACOES!F:F,MOVIMENTACOES!C:C,A108,MOVIMENTACOES!E:E,"Saída") -> 3 | G108: =E108-F108 -> 4 | H108: =IF(G108=0, "Faltando", IF(G108<=3, "Atenção", "OK")) -> OK | I108: =VLOOKUP(A108, PRODUTOS!A:H, 3, FALSE) -> SIGBP
A109: 200052413 | B109: =VLOOKUP(A109,produto,2,0) -> LUVA LATEX P COM 100 UND | C109: =IFERROR(VLOOKUP(A109,PRODUTOS!A:E,5,FALSE), "Categoria não encontrada") -> EPI | D109: =IFERROR(VLOOKUP(A109,PRODUTOS!A:E,4,FALSE), "Categoria não encontrada") -> UN | E109: =SUMIFS(MOVIMENTACOES!F:F,MOVIMENTACOES!C:C,A109,MOVIMENTACOES!E:E,"Entrada") -> 6 | F109: =SUMIFS(MOVIMENTACOES!F:F,MOVIMENTACOES!C:C,A109,MOVIMENTACOES!E:E,"Saída") -> 2 | G109: =E109-F109 -> 4 | H109: =IF(G109=0, "Faltando", IF(G109<=3, "Atenção", "OK")) -> OK | I109: =VLOOKUP(A109, PRODUTOS!A:H, 3, FALSE) -> SIGBP
A110: 200052414 | B110: =VLOOKUP(A110,produto,2,0) -> LUVA LATEX M(8) COM 100 UND | C110: =IFERROR(VLOOKUP(A110,PRODUTOS!A:E,5,FALSE), "Categoria não encontrada") -> EPI | D110: =IFERROR(VLOOKUP(A110,PRODUTOS!A:E,4,FALSE), "Categoria não encontrada") -> UN | E110: =SUMIFS(MOVIMENTACOES!F:F,MOVIMENTACOES!C:C,A110,MOVIMENTACOES!E:E,"Entrada") -> 4 | F110: =SUMIFS(MOVIMENTACOES!F:F,MOVIMENTACOES!C:C,A110,MOVIMENTACOES!E:E,"Saída") -> 0 | G110: =E110-F110 -> 4 | H110: =IF(G110=0, "Faltando", IF(G110<=3, "Atenção", "OK")) -> OK | I110: =VLOOKUP(A110, PRODUTOS!A:H, 3, FALSE) -> SIGBP
A111: 200075793 | B111: =VLOOKUP(A111,produto,2,0) -> MASCARA DE PROTEÇÃO PFF2 FILTRO N95 COM VALVULA SUPER SAFETY (azul) | C111: =IFERROR(VLOOKUP(A111,PRODUTOS!A:E,5,FALSE), "Categoria não encontrada") -> EPI | D111: =IFERROR(VLOOKUP(A111,PRODUTOS!A:E,4,FALSE), "Categoria não encontrada") -> PCT | E111: =SUMIFS(MOVIMENTACOES!F:F,MOVIMENTACOES!C:C,A111,MOVIMENTACOES!E:E,"Entrada") -> 15 | F111: =SUMIFS(MOVIMENTACOES!F:F,MOVIMENTACOES!C:C,A111,MOVIMENTACOES!E:E,"Saída") -> 3 | G111: =E111-F111 -> 12 | H111: =IF(G111=0, "Faltando", IF(G111<=3, "Atenção", "OK")) -> OK | I111: =VLOOKUP(A111, PRODUTOS!A:H, 3, FALSE) -> SIGBP
A112: 200061889 | B112: =VLOOKUP(A112,produto,2,0) -> MASCARA DE PROTEÇÃO PFF2 FILTRO N95( BRANCA) | C112: =IFERROR(VLOOKUP(A112,PRODUTOS!A:E,5,FALSE), "Categoria não encontrada") -> EPI | D112: =IFERROR(VLOOKUP(A112,PRODUTOS!A:E,4,FALSE), "Categoria não encontrada") -> UN | E112: =SUMIFS(MOVIMENTACOES!F:F,MOVIMENTACOES!C:C,A112,MOVIMENTACOES!E:E,"Entrada") -> 19 | F112: =SUMIFS(MOVIMENTACOES!F:F,MOVIMENTACOES!C:C,A112,MOVIMENTACOES!E:E,"Saída") -> 4 | G112: =E112-F112 -> 15 | H112: =IF(G112=0, "Faltando", IF(G112<=3, "Atenção", "OK")) -> OK | I112: =VLOOKUP(A112, PRODUTOS!A:H, 3, FALSE) -> SIGBP
... A133: 200001528 | B133: =VLOOKUP(A133,produto,2,0) -> LAPIS GRAFITE Nº 02 | C133: =IFERROR(VLOOKUP(A133,PRODUTOS!A:E,5,FALSE), "Categoria não encontrada") -> EXPEDIENTE | D133: =IFERROR(VLOOKUP(A133,PRODUTOS!A:E,4,FALSE), "Categoria não encontrada") -> UN | E133: =SUMIFS(MOVIMENTACOES!F:F,MOVIMENTACOES!C:C,A133,MOVIMENTACOES!E:E,"Entrada") -> 16 | F133: =SUMIFS(MOVIMENTACOES!F:F,MOVIMENTACOES!C:C,A133,MOVIMENTACOES!E:E,"Saída") -> 7 | G133: =E133-F133 -> 9 | H133: =IF(G133=0, "Faltando", IF(G133<=3, "Atenção", "OK")) -> OK | I133: =VLOOKUP(A133, PRODUTOS!A:H, 3, FALSE) -> SIGBP
A134: 200000009 | B134: =VLOOKUP(A134,produto,2,0) -> MARCADOR PARA QUADRO BRANCO | C134: =IFERROR(VLOOKUP(A134,PRODUTOS!A:E,5,FALSE), "Categoria não encontrada") -> EXPEDIENTE | D134: =IFERROR(VLOOKUP(A134,PRODUTOS!A:E,4,FALSE), "Categoria não encontrada") -> UN | E134: =SUMIFS(MOVIMENTACOES!F:F,MOVIMENTACOES!C:C,A134,MOVIMENTACOES!E:E,"Entrada") -> 9 | F134: =SUMIFS(MOVIMENTACOES!F:F,MOVIMENTACOES!C:C,A134,MOVIMENTACOES!E:E,"Saída") -> 1 | G134: =E134-F134 -> 8 | H134: =IF(G134=0, "Faltando", IF(G134<=3, "Atenção", "OK")) -> OK | I134: =VLOOKUP(A134, PRODUTOS!A:H, 3, FALSE) -> SIGBP
A135: 200082939 | B135: =VLOOKUP(A135,produto,2,0) -> BLOCO DE PAPEL AUTO ADESIVO POST IT 38X50MM 100 FOLHAS | C135: =IFERROR(VLOOKUP(A135,PRODUTOS!A:E,5,FALSE), "Categoria não encontrada") -> EXPEDIENTE | D135: =IFERROR(VLOOKUP(A135,PRODUTOS!A:E,4,FALSE), "Categoria não encontrada") -> PCT | E135: =SUMIFS(MOVIMENTACOES!F:F,MOVIMENTACOES!C:C,A135,MOVIMENTACOES!E:E,"Entrada") -> 8 | F135: =SUMIFS(MOVIMENTACOES!F:F,MOVIMENTACOES!C:C,A135,MOVIMENTACOES!E:E,"Saída") -> 4 | G135: =E135-F135 -> 4 | H135: =IF(G135=0, "Faltando", IF(G135<=3, "Atenção", "OK")) -> OK | I135: =VLOOKUP(A135, PRODUTOS!A:H, 3, FALSE) -> SIGBP
A136: 200000047 | B136: =VLOOKUP(A136,produto,2,0) -> POTES DE VIDRO 210ml | C136: =IFERROR(VLOOKUP(A136,PRODUTOS!A:E,5,FALSE), "Categoria não encontrada") -> EXPEDIENTE | D136: =IFERROR(VLOOKUP(A136,PRODUTOS!A:E,4,FALSE), "Categoria não encontrada") -> UN | E136: =SUMIFS(MOVIMENTACOES!F:F,MOVIMENTACOES!C:C,A136,MOVIMENTACOES!E:E,"Entrada") -> 12 | F136: =SUMIFS(MOVIMENTACOES!F:F,MOVIMENTACOES!C:C,A136,MOVIMENTACOES!E:E,"Saída") -> 8 | G136: =E136-F136 -> 4 | H136: =IF(G136=0, "Faltando", IF(G136<=3, "Atenção", "OK")) -> OK | I136: =VLOOKUP(A136, PRODUTOS!A:H, 3, FALSE) -> DOAÇÃO
A137: 200062977 | B137: =VLOOKUP(A137,produto,2,0) -> TINTA PARA CARIMBO COR AZUL DE 40ML | C137: =IFERROR(VLOOKUP(A137,PRODUTOS!A:E,5,FALSE), "Categoria não encontrada") -> EXPEDIENTE | D137: =IFERROR(VLOOKUP(A137,PRODUTOS!A:E,4,FALSE), "Categoria não encontrada") -> UN | E137: =SUMIFS(MOVIMENTACOES!F:F,MOVIMENTACOES!C:C,A137,MOVIMENTACOES!E:E,"Entrada") -> 8 | F137: =SUMIFS(MOVIMENTACOES!F:F,MOVIMENTACOES!C:C,A137,MOVIMENTACOES!E:E,"Saída") -> 4 | G137: =E137-F137 -> 4 | H137: =IF(G137=0, "Faltando", IF(G137<=3, "Atenção", "OK")) -> OK | I137: =VLOOKUP(A137, PRODUTOS!A:H, 3, FALSE) -> SIGBP
A138: 200000025 | B138: =VLOOKUP(A138,produto,2,0) -> PLACA TERMOPLASTICA - ORFIT ECO BLACK NS 45 x 60cm x 3.2mm MINI Perforated | C138: =IFERROR(VLOOKUP(A138,PRODUTOS!A:E,5,FALSE), "Categoria não encontrada") -> MATERIAL T.O | D138: =IFERROR(VLOOKUP(A138,PRODUTOS!A:E,4,FALSE), "Categoria não encontrada") -> UN | E138: =SUMIFS(MOVIMENTACOES!F:F,MOVIMENTACOES!C:C,A138,MOVIMENTACOES!E:E,"Entrada") -> 15 | F138: =SUMIFS(MOVIMENTACOES!F:F,MOVIMENTACOES!C:C,A138,MOVIMENTACOES!E:E,"Saída") -> 11 | G138: =E138-F138 -> 4 | H138: =IF(G138=0, "Faltando", IF(G138<=3, "Atenção", "OK")) -> OK | I138: =VLOOKUP(A138, PRODUTOS!A:H, 3, FALSE) -> EFECTIV
A139: 200000027 | B139: =VLOOKUP(A139,produto,2,0) -> PLACA TERMOPLASTICA - ORFIT ECO NATUREL 45 x 60cm x 3.2mm MINI Perforated | C139: =IFERROR(VLOOKUP(A139,PRODUTOS!A:E,5,FALSE), "Categoria não encontrada") -> MATERIAL T.O | D139: =IFERROR(VLOOKUP(A139,PRODUTOS!A:E,4,FALSE), "Categoria não encontrada") -> UN | E139: =SUMIFS(MOVIMENTACOES!F:F,MOVIMENTACOES!C:C,A139,MOVIMENTACOES!E:E,"Entrada") -> 29 | F139: =SUMIFS(MOVIMENTACOES!F:F,MOVIMENTACOES!C:C,A139,MOVIMENTACOES!E:E,"Saída") -> 13 | G139: =E139-F139 -> 16 | H139: =IF(G139=0, "Faltando", IF(G139<=3, "Atenção", "OK")) -> OK | I139: =VLOOKUP(A139, PRODUTOS!A:H, 3, FALSE) -> EFECTIV
A140: 200000033 | B140: =VLOOKUP(A140,produto,2,0) -> BANCO PEQUENO AZUL | C140: =IFERROR(VLOOKUP(A140,PRODUTOS!A:E,5,FALSE), "Categoria não encontrada") -> MOVEIS | D140: =IFERROR(VLOOKUP(A140,PRODUTOS!A:E,4,FALSE), "Categoria não encontrada") -> UN | E140: =SUMIFS(MOVIMENTACOES!F:F,MOVIMENTACOES!C:C,A140,MOVIMENTACOES!E:E,"Entrada") -> 10 | F140: =SUMIFS(MOVIMENTACOES!F:F,MOVIMENTACOES!C:C,A140,MOVIMENTACOES!E:E,"Saída") -> 4 | G140: =E140-F140 -> 6 | H140: =IF(G140=0, "Faltando", IF(G140<=3, "Atenção", "OK")) -> OK | I140: =VLOOKUP(A140, PRODUTOS!A:H, 3, FALSE) -> SIGBP
...
